Workbook

Sheet codebook_short
A1: Pillar | B1: Indicator Name | C1: Programmatic Name | D1: Code | E1: Description | F1: Unit | G1: Source
A2: Talk | B2: Count of words in reporting relating to Poverty and Wellbeing | C2: talk_wb_count | D2: T001 | E2: The total number of references to selected keywords in Annual Reporting, Sustainability Reports and Websites; in this case related to Poverty & Wellbeing. | F2: Count | G2: Annual Reports, Sustainability Reports and Company Websites
A3: Talk | B3: Count of words in reporting relating to Education and Skills | C3: talk_skills_count | D3: T002 | E3: The total number of references to selected keywords in Annual Reporting, Sustainability Reports and Websites; in this case related to Education & Skills | F3: Count | G3: Annual Reports, Sustainability Reports and Company Websites
A4: Talk | B4: Count of words in reporting relating to Equality | C4: talk_equality_count | D4: T003 | E4: The total number of references to selected keywords in Annual Reporting, Sustainability Reports and Websites; in this case related to Equality | F4: Count | G4: Annual Reports, Sustainability Reports and Company Websites
A5: Talk | B5: Count of words in reporting relating to Good Business | C5: talk_gb_count | D5: T004 | E5: The total number of references to selected keywords in Annual Reporting, Sustainability Reports and Websites; in this case related to Good Business | F5: Count | G5: Annual Reports, Sustainability Reports and Company Websites
A6: Talk | B6: Count of words in reporting relating to Climate | C6: talk_climate_count | D6: T005 | E6: The total number of references to selected keywords in Annual Reporting, Sustainability Reports and Websites; in this case related to Climate | F6: Count | G6: Annual Reports, Sustainability Reports and Company Websites
A7: Talk | B7: Count of words in reporting relating to Partnership | C7: talk_partnership_count | D7: T006 | E7: The total number of references to selected keywords in Annual Reporting, Sustainability Reports and Websites; in this case related to Partnership | F7: Count | G7: Annual Reports, Sustainability Reports and Company Websites
A8: Talk | B8: Count of words in reporting relating to Justice | C8: talk_justice_count | D8: T007 | E8: The total number of references to selected keywords in Annual Reporting, Sustainability Reports and Websites; in this case related to Justice | F8: Count | G8: Annual Reports, Sustainability Reports and Company Websites
A9: Talk | B9: Proportion of words in reporting relating to Poverty and Wellbeing | C9: talk_wb_pct | D9: T008 | E9: The total number of references to selected keywords in Annual Reporting, Sustainability Reports and Websites as a proportion of total word count in analysed text; in this case related to Poverty & Wellbeing | F9: Count | G9: Annual Reports, Sustainability Reports and Company Websites
A10: Talk | B10: Proportion of words in reporting relating to Education and Skills | C10: talk_skills_pct | D10: T009 | E10: The total number of references to selected keywords in Annual Reporting, Sustainability Reports and Websites as a proportion of total word count in analysed text; in this case related to Education & Skills | F10: Percentage | G10: Annual Reports, Sustainability Reports and Company Websites
A11: Talk | B11: Proportion of words in reporting relating to Equality | C11: talk_equality_pct | D11: T010 | E11: The total number of references to selected keywords in Annual Reporting, Sustainability Reports and Websites as a proportion of total word count in analysed text; in this case related to Equality | F11: Percentage | G11: Annual Reports, Sustainability Reports and Company Websites
A12: Talk | B12: Proportion of words in reporting relating to Good Business | C12: talk_gb_pct | D12: T011 | E12: The total number of references to selected keywords in Annual Reporting, Sustainability Reports and Websites as a proportion of total word count in analysed text; in this case related to Good Business | F12: Percentage | G12: Annual Reports, Sustainability Reports and Company Websites
... A127: Partnership | B127: Hours dedicated to charity | C127: partnership_hours | D127: P010 | E127: The number of hours a company's employees have spent volunteering for charitable and community organisations. | F127: Hours | G127: Annual Report, Sustainability Report
A128: Partnership | B128: Community, charity and social contributions reach | C128: partnership_contribs_reach | D128: P011
A129: Partnership | B129: Community, charity and social contributions (£) | C129: partnership_contribs | D129: P012 | E129: The total amount or value of charitable donations and volunteering by a company/group. | F129: GBP | G129: Annual Report, Sustainability Report
A130: Justice | B130: Number of fines relating to Planet | C130: justice_fines_planet_count | D130: J001 | E130: The total number of fines, settlements and other financial penalties related to environmental factors issued to the company/group by UK and US regulators since 2016. | F130: Count | G130: The regulatory bodies included are as follows, with the USA bodies having been compiled by Good Jobs First's Violations Tracker (https://www.goodjobsfirst.org/violation-tracker): ICO (UK), FMCSA (USA), USAO (USA), EPA (USA), OFCCP (USA), FRA (USA), OSHA (USA), CFTC (USA), DOJ (USA), ACPD (USA), MSHA (USA), EA (UK), BSEE (USA), OFGEM (UK), OFCOM (UK), Gambling Commission (UK), HSE (UK), OFAC (USA), FED (USA), SFO (UK), FCA (UK), FAA (USA)
A131: Justice | B131: Number of fines relating to People | C131: justice_fines_people_count | D131: J002 | E131: The total value of fines, settlements and other financial penalties related to social factors issued to the company/group by UK and US regulators since 2016. | F131: Count | G131: The regulatory bodies included are as follows, with the USA bodies having been compiled by Good Jobs First's Violations Tracker (https://www.goodjobsfirst.org/violation-tracker): ICO (UK), FMCSA (USA), USAO (USA), EPA (USA), OFCCP (USA), FRA (USA), OSHA (USA), CFTC (USA), DOJ (USA), ACPD (USA), MSHA (USA), EA (UK), BSEE (USA), OFGEM (UK), OFCOM (UK), Gambling Commission (UK), HSE (UK), OFAC (USA), FED (USA), SFO (UK), FCA (UK), FAA (USA)
A132: Justice | B132: Number of human rights accusations not responded to | C132: justice_accusations_response | D132: J003 | E132: The absolute number of human rights accusations, compiled by the Business and Human Rights Resource Centre, that have not been replied to by the company. | F132: Count | G132: BHRRC https://www.business-humanrights.org/
A133: Justice | B133: Response rate to human rights accusations | C133: justice_accusations_rate | D133: J004 | E133: The number of human rights accusations compiled by the Business and Human Rights Resource Centre that a company has responded to as a proportion of the total number of accusations compiled by the Centre. | F133: Percentage | G133: BHRRC https://www.business-humanrights.org/
A134: Justice | B134: BHRRC Modern Slavery Report ranking | C134: justice_slavery | D134: J005 | E134: A ranking by the Business and Human Rights Resource Centres of the FTSE100 companies on their compliance with the Modern Slavery Act. | F134: Rank | G134: BHRRC https://www.business-humanrights.org/
A135: Justice | B135: Value of People fines (£) | C135: justice_fines_people_value | D135: J006 | E135: The total value of fines, settlements and other financial penalties related to social factors issued to the company/group by UK and US regulators since 2016. | F135: GBP | G135: The regulatory bodies included are as follows, with the USA bodies having been compiled by Good Jobs First's Violations Tracker (https://www.goodjobsfirst.org/violation-tracker): ICO (UK), FMCSA (USA), USAO (USA), EPA (USA), OFCCP (USA), FRA (USA), OSHA (USA), CFTC (USA), DOJ (USA), ACPD (USA), MSHA (USA), EA (UK), BSEE (USA), OFGEM (UK), OFCOM (UK), Gambling Commission (UK), HSE (UK), OFAC (USA), FED (USA), SFO (UK), FCA (UK), FAA (USA)
A136: Justice | B136: Value of People fines as a proportion of revenue (%) | C136: justice_fines_people_value_revenue | D136: J007 | E136: The total value of fines, settlements and other financial penalties related to social factors issued to the company/group by UK and US regulators since 2016 as a proportion of total revenue reported by the company/group in the most recently reported year. | F136: Percentage | G136: The regulatory bodies included are as follows, with the USA bodies having been compiled by Good Jobs First's Violations Tracker (https://www.goodjobsfirst.org/violation-tracker): ICO (UK), FMCSA (USA), USAO (USA), EPA (USA), OFCCP (USA), FRA (USA), OSHA (USA), CFTC (USA), DOJ (USA), ACPD (USA), MSHA (USA), EA (UK), BSEE (USA), OFGEM (UK), OFCOM (UK), Gambling Commission (UK), HSE (UK), OFAC (USA), FED (USA), SFO (UK), FCA (UK), FAA (USA)
A137: Justice | B137: Value of Planet fines (£) | C137: justice_fines_planet_value | D137: J008 | E137: The total value of fines, settlements and other financial penalties related to environmental factors issued to the company/group by UK and US regulators since 2016. | F137: GBP | G137: The regulatory bodies included are as follows, with the USA bodies having been compiled by Good Jobs First's Violations Tracker (https://www.goodjobsfirst.org/violation-tracker): ICO (UK), FMCSA (USA), USAO (USA), EPA (USA), OFCCP (USA), FRA (USA), OSHA (USA), CFTC (USA), DOJ (USA), ACPD (USA), MSHA (USA), EA (UK), BSEE (USA), OFGEM (UK), OFCOM (UK), Gambling Commission (UK), HSE (UK), OFAC (USA), FED (USA), SFO (UK), FCA (UK), FAA (USA)
A138: Justice | B138: Value of Planet fines as a proportion of revenue (%) | C138: justice_fines_planet_value_revenue | D138: J009 | E138: The total value of fines, settlements and other financial penalties related to environmental factors issued to the company/group by UK and US regulators since 2016 as a proportion of total revenue reported by the company/group in the most recently reported year. | F138: Percentage | G138: The regulatory bodies included are as follows, with the USA bodies having been compiled by Good Jobs First's Violations Tracker (https://www.goodjobsfirst.org/violation-tracker): ICO (UK), FMCSA (USA), USAO (USA), EPA (USA), OFCCP (USA), FRA (USA), OSHA (USA), CFTC (USA), DOJ (USA), ACPD (USA), MSHA (USA), EA (UK), BSEE (USA), OFGEM (UK), OFCOM (UK), Gambling Commission (UK), HSE (UK), OFAC (USA), FED (USA), SFO (UK), FCA (UK), FAA (USA)
A139: Justice | B139: Number of upheld employment tribunal cases | C139: justice_et_upheld | D139: J010 | E139: The total number of UK Employment Tribunal cases since 2017 involving the company which saw the Tribunal uphold at least one of the claims of the employee/former employee. | F139: Count | G139: UK Employment Tribunal
A140: Justice | B140: Number of upheld employment tribunal cases per employee | C140: justice_et_upheld_employees | D140: J011 | E140: The total number of UK Employment Tribunal cases since 2017 involving the company which saw the Tribunal uphold at least one of the claims of the employee/former employee as a proportion of total number of employees. | F140: Percentage | G140: UK Employment Tribunal
... A144: Misc | B144: Number of employees in previous year | C144: misc_employees_previous | D144: M002 | E144: The total number of people employed by a company/group in the previously reported year. If reported, we have used FTE or average number of employees. | F144: Count | G144: Annual Report
A145: Misc | B145: Market capitalisation | C145: misc_cap | D145: M003 | G145: London Stock Exchange

Sheet codebook_full
A1: Indicator Name | B1: Pillar | C1: Code | D1: Logical Order | E1: Programmatic Name | F1: On website? | G1: Send to FTSE? | H1: Used for C100 | I1: Methodology | J1: Scaled | K1: Search terms | L1: Description | M1: Unit | N1: Data Type | O1: Source | P1: Data location | Q1: What needs to happen in the code | R1: Exclude Tickers | S1: Imputation | T1: Normalisation | U1: Transform | V1: Negative Weight | W1: Reward/Penalty
A2: Scope 3 Score | B2: Climate | C2: C023 | D2: 1 | E2: climate_scope3_score | I2: Score based on Scope 3 emissions reporting: - If Scope 3 emissions are not reported, score = 0 - If Scope 3 emissions are reported and < Scope 1&2, score = 1 - If Scope 3 emissions are reported and > Scope 1&2, score = 2 | J2: None | L2: This indicator captures whether a company's Scope 3 reporting is accurate. This is based upon research findings that Scope 3 emissions are typically higher than Scope 1 and 2. Our methodology is as follows: - If Scope 3 emissions are not reported, score = 0 - If Scope 3 emissions are reported and < Scope 1&2, score = 1 - If Scope 3 emissions are reported and > Scope 1&2, score = 2 | M2: 0/1/2 | N2: Numeric | O2: Bespoke | P2: Programmatic | Q2: Score the Scope 3 emissions 0, 1 or 2
A3: Total Scope 3 Greenhouse Gas Emissions | B3: Climate | C3: C019 | D3: 2 | E3: climate_scope3 | F3: 1 | G3: 1 | H3: 1 | I3: PLEASE FLAG WHAT'S INCLUDED (ie. employee travel). Please find total Scope 3 emissions reported in annual reports. | J3: None | K3: scope 3, emissions | L3: The amount of Scope 3 emissions (emissions along a company's value chain that they are indirectly responsible for) in tonnes. | M3: Tonnes of CO2e | N3: Numeric | O3: Annual Report, Sustainability Report | P3: Annual Report | S3: Max | T3: Reverse Normalise | U3: Square Root Transform | V3: 1 | W3: -1
A4: Total Scope 1 & Scope 2 Greenhouse Gas Emissions | B4: Climate | C4: C001 | D4: 3 | E4: climate_scope12 | F4: 1 | G4: 1 | H4: 1 | I4: The sum of Scope 1 and Scope 2 emissions. If they give one figure and don't specify whether it's Market Based or Location Based, take the figure available. If they give two figures, choose market-based. If they just provide location-based, use that. | J4: By revenue | K4: scope, scope 1, scope 2, emissions | L4: The amount of Scope 1 (all direct emissions that are controlled or owned by an organisation) and Scope 2 (indirect emissions associated with the purchase of electricity, steam, heat, or cooling) emissions reported by a company in its most recent annual report, as measured in tonnes of carbon dioxide equivalent (CO2e). Market-based Scope 2 emissions are taken where available as they represent the emissions a company is responsible for through its purchasing decisions, as opposed to 'location-based' which represents the average emissions intensity of grids on which energy consumption occurs. | M4: Tonnes of CO2e | N4: Numeric | O4: Annual Report, Sustainability Report | P4: Annual Report | S4: Max | T4: Reverse Normalise | U4: Square Root Transform | V4: 1 | W4: -1
A5: Total Water Consumption | B5: Climate | C5: C004 | D5: 4 | E5: climate_water | F5: 1 | G5: 1 | H5: 1 | I5: Find Total Water Consumption in the annual report. The number should be readily available, however, if it is not, please add any figure reported as either water 'consumption', 'use' or 'extraction' and mark clearly in the FLAG column. Be careful to check the units. | J5: By revenue | K5: water, consumption | L5: Total Water Consumption includes both direct (operational) and indirect (supply-chain) water footprints. | M5: Cubic Metres | N5: Numeric | O5: Annual Report, Sustainability Report | P5: Annual Report | S5: Max | T5: Reverse Normalise | U5: Square Root Transform | V5: 1 | W5: -1
A6: Total Energy Consumption | B6: Climate | C6: C007 | D6: 5 | E6: climate_energy | F6: 1 | G6: 1 | H6: 1 | I6: Find value and convert to MWh (ie. using Google) | J6: By revenue | K6: energy | L6: The total energy consumed by a company per year. | M6: MWH | N6: Numeric | O6: Annual Report, Sustainability Report | P6: Annual Report | S6: Max | T6: Reverse Normalise | U6: Square Root Transform | V6: 1 | W6: -1
A7: % Energy Usage from Renewable Sources | B7: Climate | C7: C005 | D7: 6 | E7: climate_renewable_energy | F7: 1 | G7: 1 | H7: 1 | I7: The figure is calculated as the percentage of total energy usage that is accounted for by energy from renewable sources. Please note that it is energy, not electricity. | J7: None | K7: renewable energy, renewable, renewables | L7: The percentage of total energy used by a company/group that is from a renewable source (e.g. wind, solar, etc). | M7: Percentage | N7: Numeric | O7: Annual Report, Sustainability Report | P7: Annual Report | S7: 0 | V7: 1 | W7: 1
A8: % Electricity Usage from Renewable Sources | B8: Climate | C8: C006 | D8: 7 | E8: climate_renewable_electricity | F8: 1 | G8: 1 | H8: 1 | I8: The figure is calculated as the percentage of total electricity usage that is accounted for by energy from renewable sources. Please note that it is electricity not energy. | J8: None | K8: electricity, renewable sources | L8: The percentage of total electricity used by a company/group that is from a renewable source (e.g. wind, solar, etc). | M8: Percentage | N8: Numeric | O8: Annual Report, Sustainability Report | P8: Annual Report | S8: 0 | V8: 1 | W8: 1
A9: Total Waste Produced | B9: Climate | C9: C018 | D9: 8 | E9: climate_waste | F9: 1 | G9: 1 | H9: 1 | I9: The total amount of waste produced by a company. Please note the units and convert into tonnes. | J9: By revenue | K9: waste | L9: The total amount of waste produced by a company. | M9: Tonnes | N9: Numeric | O9: Annual Report, Sustainability Report | P9: Annual Report | S9: Max | T9: Reverse Normalise | U9: Square Root Transform | V9: 1 | W9: -1
A10: % Waste Recycled or Re-used | B10: Climate | C10: C010 | D10: 9 | E10: climate_waste_recycled | F10: 1 | G10: 1 | H10: 1 | I10: The absolute percentage of total waste produced by a company/group that is reported as re-used or recycled. This can be found in the annual report. | J10: None | K10: recycled, reuse, waste | L10: The absolute percentage of total waste produced by a company/group that is reported as re-used or recycled. | M10: Percentage | N10: Numeric | O10: Annual Report, Sustainability Report | P10: Annual Report | S10: 0 | V10: 1 | W10: 1
A11: % Waste to Landfill | B11: Climate | C11: C009 | D11: 10 | E11: climate_waste_landfill | F11: 1 | G11: 1 | H11: 1 | I11: PLEASE NOTE: DON'T INFER FROM WASTE RECYCLED - THEY ARE NOT THE SAME FIGURE. Find the absolute percentage of total waste produced by a company/group that is sent to landfill in annual reports. You may need to add up a variety of numbers. Please write all numbers in the Flag column. | J11: None | K11: landfill, waste | L11: The absolute percentage of total waste produced by a company/group that is sent to landfill. | M11: Percentage | N11: Numeric | O11: Annual Report, Sustainability Report | P11: Annual Report | S11: Max | V11: -1 | W11: -1
A12: CDP Water Security Rating | B12: Climate | C12: C014 | D12: 11 | E12: climate_cdp_water | F12: 1 | G12: 1 | H12: 1 | I12: Go to the CDP website (https://www.cdp.net/en/search) and search for the company name. Go to their Water Security response and find the letter that corresponds to their water security rating (e.g. A - D-). | J12: None | K12: CDP, CDP Water | L12: The Carbon Disclosure Project (CDP) runs the global disclosure system for companies to manage their environmental impacts, and invites reporting on current practices and procedures, risks and opportunities, and strategy. The CDP Water Security Rating involves reporting on current practices and procedures, risks and opportunities, and targets/strategy. It is scored A to D- based on a company's questionnaire submission. | M12: Grade of A to F | N12: Categorical | O12: CDP https://www.cdp.net/en/companies/companies-scores | P12: Programmatic | Q12: Figure out if we can scrape. If not, change to Additional Indicators | V12: 1 | W12: 1
A13: CDP Forests Rating | B13: Climate | C13: C013 | D13: 12 | E13: climate_cdp_forestry | F13: 1 | G13: 1 | H13: 1 | I13: Go to the CDP website (https://www.cdp.net/en/search) and search for the company name. Go to their Forests response and find the letter that corresponds to their forestry rating (e.g. A - D-). | J13: None | K13: CDP, CDP Forests | L13: The Carbon Disclosure Project (CDP) runs the global disclosure system for companies to manage their environmental impacts, and invites reporting on current practices and procedures, risks and opportunities, and strategy. The CDP Timber and Forestry Rating records data on commodity consumption, origin and certifications. It is scored A to D- based on a company's questionnaire submission. | M13: Grade of A to F | N13: Categorical | O13: CDP https://www.cdp.net/en/companies/companies-scores | P13: Programmatic | Q13: Scrape | V13: 1 | W13: 1
A14: CDP Climate Rating | B14: Climate | C14: C012 | D14: 13 | E14: climate_cdp_climate | F14: 1 | G14: 1 | H14: 1 | I14: Go to the CDP website (https://www.cdp.net/en/search) and search for the company name. Go to their Climate Change response and find the letter that corresponds to their climate rating (e.g. A - D-). | J14: None | K14: CDP, CDP Climate | L14: The Carbon Disclosure Project (CDP) runs the global disclosure system for companies to manage their environmental impacts, and invites reporting on current practices and procedures, risks and opportunities, and strategy. The CDP Climate Rating records data on emissions, climate risk and opportunities, etc, and is scored A to D- based on a company's questionnaire submission. | M14: Grade of A to F | N14: Categorical | O14: CDP https://www.cdp.net/en/companies/companies-scores | P14: Programmatic | Q14: Scrape | V14: 1 | W14: 1
A15: % Ethnic Minority Pay Gap in UK | B15: Equality | C15: E013 | D15: 14 | E15: equality_bame_pay | F15: 1 | G15: 1 | H15: 0 | I15: UK Data ONLY (PLEASE ADD GLOBAL FIGURE TO FLAG COLUMN). The percentage (%) pay gap for people who are BAME (Black Asian and Minority Ethnic Group). | J15: None | K15: ethnic minority, BAME | L15: The absolute percentage difference in pay between Black, Asian or Minority Ethnic (BAME) and non-BAME identifying employees at the company/group. | M15: Percentage | N15: Numeric | O15: Annual Report | P15: Annual Report | Q15: Score data on pay gaps as a binary in the code | S15: 100 | T15: Reverse Normalise | U15: Absolute Transform | V15: 1 | W15: -1
A16: % Median Gender Pay Gap in UK | B16: Equality | C16: E006 | D16: 15 | E16: equality_gender_pay | F16: 1 | G16: 1 | H16: 0 | J16: None | K16: gender pay gap, median gender pay | L16: The absolute percentage difference between the median pay of a company's male and female employees across the company, as reported to the UK government. | M16: Percentage | N16: Numeric | O16: GOV.uk | P16: Programmatic | Q16: Figure out if we can scrape (look at description and methodology for guidance on how subsidiaries work). If not, change to Annual Report, and add 1 in AR column | S16: Max | T16: Reverse Normalise | U16: Absolute Transform | V16: 1
A17: % Median Gender Bonus Gap in UK | B17: Equality | C17: E024 | D17: 16 | E17: equality_gender_bonus | F17: 1 | G17: 1 | H17: 0 | J17: None | L17: The median percentage difference in bonuses between a company's male and female employees in the UK. A positive gender bonus gap indicates that men are paid more than women. A negative bonus pay gap indicates that women are paid more than men. This information can be found in their UK Government Gender Pay Gap reports (https://gender-pay-gap.service.gov.uk/), Annual Reports, Sustainability reports, or on their website. This indicator is for UK employees only. A negative gender bonus gap is scored equally to no pay gap. | M17: Percentage | N17: Numeric | O17: GOV.uk | P17: Programmatic | Q17: Figure out if we can scrape (look at description and methodology for guidance on how subsidiaries work). If not, change to Annual Report, and add 1 in AR column | S17: Max | T17: Reverse Normalise | U17: Absolute Transform | V17: 1
A18: % Senior Management who are Female | B18: Equality | C18: E002 | D18: 17 | E18: equality_female_management | F18: 1 | G18: 1 | H18: 0 | I18: PLEASE NOTE - SENIOR MANAGEMENT DOES NOT INCLUDE BOARD OF DIRECTORS. Only collect if company provides this number (they should, and it would be in their annual report/gender pay report). If they do not use the term "senior management" exactly, add note about what kind of (senior) manager we've got. It might be called directors/leaders. | J18: None | K18: senior management | L18: The percentage of senior management at the company/group that are female. | M18: Percentage | N18: Numeric | O18: Annual Report, Pay Gap Report | P18: Annual Report | S18: 0 | V18: 1 | W18: 1
A19: % Employees who are Female | B19: Equality | C19: E003 | D19: 18 | E19: equality_female_employees | F19: 1 | G19: 1 | H19: 0 | I19: The percentage (%) of the total workforce at the company who are female. Please note that this should be FTE if available. It will usually be reported in annual report or gender pay reports. | J19: None | K19: women, female, employees | L19: The percentage of total employees at the company/group that are female. | M19: Percentage | N19: Numeric | O19: Annual Report, Pay Gap Report | P19: Annual Report | S19: 0 | V19: 1 | W19: 1
A20: % UK Senior Management from an Ethnic Minority Background | B20: Equality | C20: E014 | D20: 19 | E20: equality_bame_management | F20: 1 | G20: 1 | H20: 0 | I20: UK Data ONLY (PLEASE ADD GLOBAL FIGURE TO FLAG COLUMN). PLEASE NOTE - SENIOR MANAGEMENT DOES NOT INCLUDE BOARD OF DIRECTORS Senior management is not board of directors; only collect if company provides; if not "senior management" exactly, add note about what kind of (senior) manager we've got. | J20: None | K20: ethnic minority, BAME | L20: The percentage of senior management at the company who identify as Black, Asian or Minority Ethnic (BAME). | M20: Percentage | N20: Numeric | O20: Annual Report | P20: Annual Report | S20: 0 | V20: 1 | W20: 1
A21: % UK Employees from an Ethnic Minority Background | B21: Equality | C21: E012 | D21: 20 | E21: equality_bame_employees | F21: 1 | G21: 1 | H21: 0 | I21: UK Data ONLY (PLEASE ADD GLOBAL FIGURE TO FLAG COLUMN). The percentage (%) of the total workforce at the company who are BAME (Black Asian and Minority Ethnic Group). | J21: None | K21: ethnic minority, BAME | L21: The percentage of total employees at the company/group who identify as Black, Asian or Minority Ethnic (BAME). | M21: Percentage | N21: Numeric | O21: Annual Report | P21: Annual Report | S21: 0 | V21: 1 | W21: 1
A22: % UK Employees who are LGBTQ+ | B22: Equality | C22: E015 | D22: 21 | E22: equality_lgbt_employees | F22: 1 | G22: 1 | H22: 0 | I22: Find value in annual report. It may also be in a diversity / gender report too. If missing, write 'MISSING'. | J22: None | K22: LGBTQIA+, LGBT, LGBTQ, sexual orientation | L22: The percentage of total employees at the company/group who identify as Lesbian, Gay, Bisexual, Transgender, Queer or other non-binary groups (LGBTQ+). | M22: Percentage | N22: Numeric | O22: Annual Report | P22: Annual Report | S22: 0 | V22: 1 | W22: 1
A23: % UK Senior Management who are LGBTQ+ | B23: Equality | C23: E017 | D23: 22 | E23: equality_lgbt_management | F23: 1 | G23: 1 | H23: 0 | I23: UK Data ONLY (PLEASE ADD GLOBAL FIGURE TO FLAG COLUMN). PLEASE NOTE - SENIOR MANAGEMENT DOES NOT INCLUDE BOARD OF DIRECTORS Senior management is not board of directors; only collect if company provides; if not "senior management" exactly, add note about what kind of (senior) manager we've got. | J23: None | K23: LGBTQIA+, LGBT, LGBTQ, sexual orientation | L23: The percentage of senior management at the company/group who identify as LGBTQ+. | M23: Percentage | N23: Numeric | O23: Annual Report | P23: Annual Report | S23: 0 | V23: 1 | W23: 1
A24: % UK Employees who are Disclosed as Disabled | B24: Equality | C24: E018 | D24: 23 | E24: equality_disability_employees | F24: 1 | G24: 1 | H24: 0 | I24: Find value in annual report. It may also be in a diversity report too. If missing, write 'MISSING'. | J24: None | K24: disabled, disability, disabilities | L24: The percentage of total employees at the company/group with disclosed disabilities. | M24: Percentage | N24: Numeric | O24: Annual Report | P24: Annual Report | S24: 0 | V24: 1 | W24: 1
A25: % UK Senior Management who are Disclosed as Disabled | B25: Equality | C25: E020 | D25: 24 | E25: equality_disability_management | F25: 1 | G25: 1 | H25: 0 | I25: UK Data ONLY (PLEASE ADD GLOBAL FIGURE TO FLAG COLUMN). PLEASE NOTE - SENIOR MANAGEMENT DOES NOT INCLUDE BOARD OF DIRECTORS Senior management is not board of directors; only collect if company provides; if not "senior management" exactly, add note about what kind of (senior) manager we've got. | J25: None | K25: disabled, disability, disabilities | L25: The percentage of senior management at the company/group who are disclosed as disabled. | M25: Percentage | N25: Numeric | O25: Annual Report | P25: Annual Report | S25: 0 | V25: 1 | W25: 1
A26: % Directors who are Female | B26: Equality | C26: E008 | D26: 25 | E26: equality_gender_directors | F26: 1 | G26: 1 | H26: 0 | I26: The proportion of a company’s board of directors that is female, not including secretaries. As there has been a historic trend of male dominated boards and the relative few numbers of people on a board we have made the decision that the larger proportion the better. This indicator includes non-executive directors. This information should be in the annual report and on the website. | J26: None | K26: directors, board of directors | L26: The proportion of a company’s board of directors that is female (excluding secretaries). As there has been a historic trend of male-dominated boards, we have made the decision that the larger proportion of females on the board, the better. | M26: Percentage | N26: Numeric | O26: Annual Report, Gender Pay Gap Report | P26: Programmatic | Q26: Scrape | S26: 0 | V26: 1 | W26: 1
A27: % New Directors (appointed in past three years) who are Female | B27: Equality | C27: E009 | D27: 26 | E27: equality_gender_appointments | F27: 1 | G27: 1 | H27: 0 | I27: Any new Directors are counted if they were appointed in the period up to three years before the Data of the most recent update of the Responsibility 100 Index, where the Data of appointment is taken to be the Data that their appointment was announced on Companies House. | J27: None | K27: directors, board of directors, female | L27: The proportion of recent hires (over the past three years) of directors to a company’s board who are female. Given that very few of the FTSE 100 boards were evenly proportioned, and that the highest hiring proportion is 75% we have decided that higher a hiring proportion of females is better. | M27: Percentage | N27: Numeric | O27: Annual Report | P27: Programmatic | Q27: Scrape | S27: 0 | V27: 1 | W27: 1
A28: Length of Primary Parental Leave | B28: Equality | C28: E004 | D28: 27 | E28: equality_leave_primary | F28: 1 | G28: 1 | H28: 0 | I28: The total amount of paid primary parental leave (sometimes known as maternity leave). The figure we collect represents the amount of paid leave, supplementary to statutory parental leave. I.e. if a company offers 26 weeks fully paid leave, plus 18 weeks statutory pay, we collect the 26 week figure. If a company offers 8 weeks at 90% pay, we collect 8x0.9 = 7.2 weeks. | J28: None | K28: parental leave | L28: The total length of fully paid maternity leave provided by the company/group, according to their maternity/paternity policy where one exists. | M28: Weeks | N28: Numeric | O28: Maternity/Paternity Policy, Annual Report | P28: Annual Report | S28: 0 | V28: 1 | W28: 1
A29: Length of Secondary Parental Leave | B29: Equality | C29: E005 | D29: 28 | E29: equality_leave_secondary | F29: 1 | G29: 1 | H29: 0 | I29: The total amount of paid secondary parental leave (sometimes known as paternity leave). The figure we collect represents the amount of paid leave, supplementary to statutory parental leave. | J29: None | K29: parental leader | L29: The total length of fully paid parental leave provided by the company/group to 'secondary' parental figures', according to their maternity/paternity policy where one exists. | M29: Weeks | N29: Numeric | O29: Maternity/Paternity Policy, Annual Report | P29: Annual Report | S29: 0 | V29: 1 | W29: 1
A30: Level of WISE Membership | B30: Membership | C30: E011 | D30: 29 | E30: equality_wise_level | F30: 1 | G30: 1 | H30: 0 | I30: This indicator discloses the level of a company's membership in the WISE campaign (Women in Science and Engineering). 1 indicates the company is an Online Member; 2 indicates Core Member; 3 indicates Premium Member; 4 indicates Strategic Partner. This can be found in annual reports or on the company's website. | J30: None | K30: WISE membership, women in stem | L30: This indicator discloses the level of a company's membership in the WISE campaign (Women in Science and Engineering). 1 indicates the company is an Online Member; 2 indicates Core Member; 3 indicates Premium Member; 4 indicates Strategic Partner. | M30: 4/3/2/1/0 | N30: Categorical | O30: WISE Campaign https://www.wisecampaign.org.uk/ | P30: Programmatic | Q30: Scrape | S30: 0 | V30: 1 | W30: 1
A31: % Annual Graduate / Apprentice Intake who are Female | B31: Equality | C31: E001 | D31: 30 | E31: equality_female_graduates | F31: 1 | G31: 1 | H31: 0 | I31: The percentage (%) of newly hired graduates at the company who are female. This can be found in annual report or in gender pay reports. | J31: None | K31: graduates, grads, apprentices, early careers, young people, early career opportunities | L31: The percentage of recent graduates hired by the company/group that are female. | M31: Percentage | N31: Numeric | O31: Annual Report, Pay Gap Report | P31: Annual Report | S31: 0 | V31: 1 | W31: 1
A32: Revenue | B32: Good Business | C32: G010 | D32: 31 | E32: gb_revenue | G32: 1 | H32: 0 | I32: This number can be found in the annual report, in the financial section. If it is not in GBP, take the average currecy conversion over the reporting period, or Jan-Jan if no reporting period using this tool https://docs.google.com/spreadsheets/d/1pFxv18Kp2d0EmS6BA4wrlqL_gsbwE8W0h-FLYPWFFog/edit#gid=0 | J32: None | K32: revenue | L32: The revenue of the company. | M32: GBP | N32: Numeric | O32: Yahoo Finance | P32: Annual Report | S32: 0 | V32: 1 | W32: 1
A33: Revenue 1 Year Prior | B33: Good Business | C33: G033 | D33: 32 | E33: collection_revenue_1_prior | I33: Revenue, turnover, net sales - these are all valid. They can be found in an annual report (found on companies House or on their website). If it is not in GBP, take the average currecy conversion over the reporting period, or Jan-Jan if no reporting period using this tool https://docs.google.com/spreadsheets/d/1pFxv18Kp2d0EmS6BA4wrlqL_gsbwE8W0h-FLYPWFFog/edit#gid=0 | J33: None | K33: revenue | L33: Dummy indicator to calculate revenue growth | M33: GBP | O33: Annual Report | P33: Annual Report | Q33: Pull in data from correct year
A34: Revenue 2 Years Prior | B34: Good Business | C34: G034 | D34: 33 | E34: collection_revenue_2_prior | I34: Revenue, turnover, net sales - these are all valid. They can be found in an annual report (found on companies House or on their website). For currency conversions, use this website: https://www.ofx.com/en-gb/forex-news/historical-exchange-rates/ and take the average from the last 3 years (31 Dec 2020 -- 31 Dec 2022) 0.867502 EUR: 1 GBP 0.772778 USD: 1 GBP 0.82542 CHF: 1 GBP | J34: None | K34: revenue | L34: Dummy indicator to calculate revenue growth | M34: GBP | O34: Annual Report | P34: Annual Report | Q34: Pull in data from correct year
A35: Revenue 3 Years Prior | B35: Good Business | C35: G035 | D35: 34 | E35: collection_revenue_3_prior | I35: Revenue, turnover, net sales - these are all valid. They can be found in an annual report (found on companies House or on their website). If it is not in GBP, take the average currecy conversion over the reporting period, or Jan-Jan if no reporting period using this tool https://docs.google.com/spreadsheets/d/1pFxv18Kp2d0EmS6BA4wrlqL_gsbwE8W0h-FLYPWFFog/edit#gid=0 | J35: None | K35: revenue | L35: Dummy indicator to calculate revenue growth | M35: GBP | O35: Annual Report | P35: Annual Report | Q35: Pull in data from correct year
A36: Operating Profit | B36: Good Business | C36: G036 | D36: 35 | E36: collection_profit | I36: In annual report, look for profit. Prefer operating profit. If operating profit is not present, take profit (loss) before taxation. If it is not in GBP, take the average currecy conversion over the reporting period, or Jan-Jan if no reporting period using this tool https://docs.google.com/spreadsheets/d/1pFxv18Kp2d0EmS6BA4wrlqL_gsbwE8W0h-FLYPWFFog/edit#gid=0 | J36: None | K36: profit | L36: Dummy indicator to calculate operating profit margin | M36: GBP | O36: Annual Report | P36: Annual Report | Q36: Create indicator
A37: % Operating Profit Margin | B37: Good Business | C37: G037 | D37: 36 | E37: gb_profit_revenue | I37: Programmatic - operating profit / revenue | J37: None | K37: profit margin | L37: Operating profit is the total income a company generates from sales after paying off all operating expenses, such as rent, employee payroll, equipment and inventory costs. The operating profit figure excludes gains or losses from interest, taxes and investments. Operating Profit Margin = Operating Profit / Total Revenue | M37: Percentage | O37: Annual Report | P37: Programmatic | Q37: Check that this is profit / revenue - can just do by scaling by revenue?
A38: % Average Revenue Growth Over 3 Years | B38: Good Business | C38: G011 | D38: 37 | E38: gb_revenue_growth | F38: 1 | G38: 0 | H38: 0 | I38: This number can be found in the annual report, in the financial section. Write the number for last year in the flag column and do the calculation. | J38: None | K38: revenue, revenue growth | L38: The total amount of revenue growth, as a percentage, at a company/group in the most recently reported year. | M38: Percentage (Change) | N38: Numeric | O38: Yahoo Finance | P38: Programmatic | Q38: Create indicator | T38: Normalise Around Zero | V38: 1 | W38: 1
A39: Total Tax Payable | B39: Good Business | C39: G014 | D39: 38 | E39: gb_tax | G39: 1 | H39: 0 | I39: This number can be found in the annual report, in the financial section. If it is not in GBP, take the average currecy conversion over the reporting period, or Jan-Jan if no reporting period using this tool https://docs.google.com/spreadsheets/d/1pFxv18Kp2d0EmS6BA4wrlqL_gsbwE8W0h-FLYPWFFog/edit#gid=0 | J39: None | K39: tax | L39: The total tax expense in £ of a company/group in the most recently reported year. This will most likely be disclosed alongside CEO pay in 'Remuneration' section of Annual Report. Use this converter to do a currency conversion over the dates of the AR (ideally using moneths, but do Jan-Jan if none available) https://docs.google.com/spreadsheets/d/1pFxv18Kp2d0EmS6BA4wrlqL_gsbwE8W0h-FLYPWFFog/edit#gid=0 | M39: GBP | N39: Numeric | O39: Yahoo Finance | P39: Programmatic | S39: 0 | V39: 1 | W39: 1
A40: % Effective Tax Rate | B40: Good Business | C40: G001 | D40: 39 | E40: gb_tax_effective | F40: 1 | G40: 1 | H40: 0 | I40: This is the effective tax rate for the company or group as reported for a given year. Only include this value if it is specifically defined as the 'effective tax rate'. It is often in a range between 15-27%. If it is blank, write MISSING. | J40: None | K40: effective tax rate, tax rate, adjusted tax | L40: The amount of tax a company has paid as a proportion of its income as reported within its latest consolidated income statement. | M40: Percentage | N40: Numeric | O40: Annual Report | P40: Annual Report | S40: 19(tax) | V40: 1 | W40: 1
A41: Company is a Fair Tax Mark Accredited Organisation | B41: Good Business | C41: G002 | D41: 40 | E41: gb_ftm | F41: 1 | G41: 1 | H41: 0 | I41: Visit the Fair Tax Mark Accredited website here: https://fairtaxmark.net/accredited-organisations/ and state 1 if the company is an accredited organisation, and 0 if they are not. | J41: None | K41: fair tax mark | L41: A binary variable indicating whether a company has Fair Tax Mark accreditation. The Fair Tax Mark accreditation scheme seeks to encourage and recognise businesses that pay the right amount of corporation tax at the right time and in the right place. | M41: 1/0 | N41: Binary | O41: Fair Tax Mark Website | P41: Additional Indicators | S41: 0 | V41: 1 | W41: 1
A42: Tax Payable as a Proportion of Total Profit | B42: Good Business | C42: G015 | D42: 41 | E42: gb_tax_profit | F42: 1 | G42: 0 | H42: 0 | I42: Programmatic - tax / profit | J42: None | K42: tax, profit, tax margin | L42: The total income tax expense in £ paid by a company/group as a percentage of reported profit before tax. | M42: Percentage | N42: Numeric | O42: Yahoo Finance | P42: Programmatic | Q42: Scrape | V42: 1 | W42: 1
A43: Tax Payable as a Proportion of Total Revenue | B43: Good Business | C43: G016 | D43: 42 | E43: gb_tax_revenue | F43: 1 | G43: 0 | H43: 0 | I43: Programmatic - tax / revenue | J43: None | K43: tax, revenue, tax margin | L43: The total income tax expense in £ paid by a company/group as a proportion of total revenue reported by the company/group in the most recently reported year. | M43: Percentage | N43: Numeric | O43: Yahoo Finance | P43: Programmatic | Q43: Scrape | V43: 1 | W43: 1
A44: Research & Development Investment | B44: Good Business | C44: G018 | D44: 43 | E44: gb_rd_revenue | F44: 1 | G44: 0 | H44: 0 | I44: This number can be found in the annual report, in the financial section. Use this converter to do a currency conversion over the dates of the AR (ideally using moneths, but do Jan-Jan if none available) https://docs.google.com/spreadsheets/d/1pFxv18Kp2d0EmS6BA4wrlqL_gsbwE8W0h-FLYPWFFog/edit#gid=0 | J44: By revenue | K44: research and development, r&d | L44: The total reported expenditure on research and development by a company/group as a proportion of total revenue reported by the company/group in the most recently reported year. | M44: GBP | N44: Numeric | O44: Annual Report | P44: Annual Report | U44: Square Root Transform | V44: 1 | W44: 1
A45: Total Value of CEO Remuneration | B45: Good Business | C45: G008 | D45: 44 | E45: gb_ceo | F45: 1 | G45: 1 | H45: 0 | I45: The total remuneration received by the CEO in £ in a company's latest annual report. If it is not in GBP, take the average currecy conversion over the reporting period, or Jan-Jan if no reporting period using this tool https://docs.google.com/spreadsheets/d/1pFxv18Kp2d0EmS6BA4wrlqL_gsbwE8W0h-FLYPWFFog/edit#gid=0 | J45: By revenue | K45: CEO, ratio, remuneration | L45: The total remuneration received by the CEO in £ in a company's latest annual report. | M45: GBP | N45: Numeric | O45: Annual Report | P45: Annual Report | S45: 0 | V45: 1 | W45: -1
A46: CEO Pay Ratio to Median Worker Pay | B46: Good Business | C46: G029 | D46: 45 | E46: gb_pay_ratio | F46: 1 | G46: 1 | H46: 0 | I46: Find CEO pay ratio in 'Remuneration' section of Annual Report. Choose Median pay ratio (P50) for employees. Collect X if reported as X:1. FLAG INCONSISTENT REPORTING. | J46: None | K46: median worker pay, median worker ratio | L46: The ratio of total remuneration of the CEO to the remuneration of the median UK employee. | M46: Ratio | N46: Numeric | O46: Annual Report | P46: Annual Report | S46: Max | T46: Reverse Normalise | V46: 1 | W46: -1
A47: % CEO Annual Bonus Linked to ESG Metrics | B47: Good Business | C47: G030 | D47: 46 | E47: gb_annual_bonus_esg | F47: 1 | G47: 1 | H47: 0 | I47: Find Annual Bonus or Annual Incentive Plan in 'Remuneration' section of Annual Report. Calculate total percentage weighting of annual bonus that's linked to ESG metrics (ie. emissions, renewables, diversity) - if it could be an R100 indicator, count it | J47: None | K47: annual bonus, annual incentive, remuneration | L47: The total percentage of CEO Annual Bonus that is linked to ESG metrics | M47: Percentage | N47: Numeric | O47: Annual Report | P47: Annual Report | S47: 0 | V47: 1 | W47: 1
A48: % CEO Long Term Incentive Plan Linked to ESG Metrics | B48: Good Business | C48: G031 | D48: 47 | E48: gb_ltip_esg | F48: 1 | G48: 1 | H48: 0 | I48: Find Long Term Incentive Plan (LTIP) or Performance Share Plan (PSP) in the 'Remuneration' section of Annual Report. Calculate total percentage weighting of LTIP that's linked to ESG metrics (ie. emissions, renewables, diversity) - if it could be an R100 indicator, count it | J48: None | K48: ltip, long term incentive plan, remuneration | L48: The total percentage of a CEO's long term incentive plan (LTIP) linked to ESG metrics | M48: Percentage | N48: Numeric | O48: Annual Report | P48: Annual Report | S48: 0 | V48: 1 | W48: 1
A49: % Revenue Not From Tax Havens | B49: Good Business | C49: G032 | D49: 48 | E49: gb_tax_haven_rev | F49: 1 | G49: 1 | H49: 0 | I49: Look for company CbC (Country by Country) Reports. Take the percentage of revenue in countries | J49: None | K49: revenue, tax, tax havens | L49: The proportion of revenue not from low-tax jurisdictions (countries with a Tax Justice Network Tax Haven score over 75), as published in Country-by-Country tax reports. Public disclosure of these CbC reports will become mandatory in EU law in 2024. | M49: Percentage | N49: Numeric | O49: CbC Reporting | P49: Programmatic | Q49: Scrape | S49: 0 | V49: 1 | W49: 1
A50: Average Rating on Glassdoor | B50: Good Business | C50: P003 | D50: 49 | E50: partnership_glassdoor_rating | F50: 1 | G50: 1 | H50: 0 | I50: Go to Glassdoor https://www.glassdoor.co.uk/index.htm, and write down the average rating (out of 5) | J50: None | K50: Glassdoor | L50: The average rating given to the company/group by users on Glassdoor. | M50: Rating out of 5 | N50: Numeric | O50: Glassdoor https://www.glassdoor.co.uk/index.htm | P50: Programmatic | Q50: Scrape | S50: 0 | T50: Normalise Excluding Zero | V50: 1 | W50: 1
A51: Total Number of Glassdoor Reviews | B51: Good Business | C51: P008 | D51: 50 | E51: partnership_glassdoor_reviews | G51: 1 | H51: 0 | I51: Go to Glassdoor https://www.glassdoor.co.uk/index.htm, and write down the number of reviews. | J51: None | L51: The total number of reviews of a company/group on its Glassdoor profile. | M51: Count | N51: Numeric | O51: Glassdoor https://www.glassdoor.co.uk/index.htm | P51: Programmatic | Q51: Scrape | S51: 0 | V51: 1 | W51: 1
A52: Total Number of Glassdoor Reviews per Employee | B52: Good Business | C52: P009 | D52: 51 | E52: partnership_glassdoor_reviews_employees | F52: 0 | G52: 0 | H52: 0 | I52: Go to Glassdoor https://www.glassdoor.co.uk/index.htm, and write down the number of reviews. Then divide by the number of employees. Write down calculation in the flag column. | J52: None | L52: The total number of reviews of a company/group on its Glassdoor profile as a proportion of its total number of employees. | M52: Per Employee | N52: Numeric | O52: Glassdoor https://www.glassdoor.co.uk/index.htm | P52: Programmatic | Q52: Scrape | S52: 0 | T52: Ignore | V52: 1 | W52: 1
A53: Value of Donations - £ | B53: Good Business | C53: P013 | D53: 52 | E53: charity_donations_pounds | I53: This information can first and foremost be found in Annual Reports or in Sustainability / CSR / reports. It may also be a stat that can be found on the website more generally. Value of donations does not include money in time or in kind. If it is not in GBP, take the average currecy conversion over the reporting period, or Jan-Jan if no reporting period using this tool https://docs.google.com/spreadsheets/d/1pFxv18Kp2d0EmS6BA4wrlqL_gsbwE8W0h-FLYPWFFog/edit#gid=0 | J53: By revenue | K53: donations, donated, support, community, fundraised, fundraising | L53: Donating to charitable organisations may indicate a companies' engagement with the local area and a commitment to improving the society in which the business operates. Value of donations does not include money in time or in kind. | M53: GBP | O53: Annual Report | P53: Annual Report | Q53: Either or in the code
A54: Value of Donations - hours | B54: Good Business | C54: P014 | D54: 53 | E54: charity_donations_hours | I54: This information can first and foremost be found in Annual Reports or in Sustainability / CSR / reports. It may also be a stat that can be found on the website more generally. Value of donations does not include money in time or in kind. | J54: By employees | K54: donations, donated, support, community, fundraised, fundraising, money-equivalent | L54: Donating to charitable organisations may indicate a companies' engagement with the local area and a commitment to improving the society in which the business operates. Value of donations does not include money in time or in kind. | M54: Hours | O54: Annual Report | P54: Annual Report | Q54: Either or in the code
A55: Net Assets | B55: Good Business | C55: P015 | D55: 54 | E55: gb_net_assets | I55: In annual report or companies house, look for net assets or net asset position. This should match the number for total equity. If it is not in GBP, take the average currecy conversion over the reporting period, or Jan-Jan if no reporting period using this tool https://docs.google.com/spreadsheets/d/1pFxv18Kp2d0EmS6BA4wrlqL_gsbwE8W0h-FLYPWFFog/edit#gid=0 | J55: By revenue | K55: net assets | L55: In annual report or companies house, look for net assets or net asset position. This should match the number for total equity. This will most likely be disclosed alongside CEO pay in 'Remuneration' section of Annual Report. Use this converter to do a currency conversion over the dates of the AR (ideally using moneths, but do Jan-Jan if none available) https://docs.google.com/spreadsheets/d/1pFxv18Kp2d0EmS6BA4wrlqL_gsbwE8W0h-FLYPWFFog/edit#gid=0 | M55: GBP | O55: Annual Report | P55: Annual Report
A56: Average Salary | B56: Good Business | C56: P018 | D56: 55 | E56: median_salary_current | I56: The average salary (£) of employees at the company. This will most likely be disclosed alongside CEO pay in 'Remuneration' section of Annual Report. If it is not in GBP, take the average currecy conversion over the reporting period, or Jan-Jan if no reporting period using this tool https://docs.google.com/spreadsheets/d/1pFxv18Kp2d0EmS6BA4wrlqL_gsbwE8W0h-FLYPWFFog/edit#gid=0 | J56: None | K56: salary, median employee wage | L56: The average salary (£) of employees at the company. This will most likely be disclosed alongside CEO pay in 'Remuneration' section of Annual Report. | M56: GBP | O56: Annual Report | P56: Annual Report
A57: Number of Fines Relating to 'Planet' | B57: Justice | C57: J001 | D57: 56 | E57: justice_fines_planet_count | F57: 1 | G57: 1 | H57: 0 | I57: Any fines that were announced up to three years before the Data of the most recent update of the Responsibility 100 are counted as part of this total. It concerns all fines relating to the 'planet' (e.g. environment). Write down all the fines in the flag column & add them up. | J57: By revenue | K57: fines, environmental fines | L57: The total number of fines, settlements and other financial penalties related to environmental factors issued to the company/group by UK and US regulators over the past three years. | M57: Count | N57: Numeric | O57: Violation Tracker US/UK | P57: Programmatic | Q57: Scrape | S57: 0 | V57: -1 | W57: -1
A58: Number of Fines Relating to 'People' | B58: Justice | C58: J002 | D58: 57 | E58: justice_fines_people_count | F58: 1 | G58: 1 | H58: 0 | I58: Any fines that were announced up to three years before the Data of the most recent update of the Responsibility 100 are counted as part of this total. It concerns all fines relating to the 'people' (e.g. human rights, modern slavery, etc). Write down all the fines in the flag column & add them up. | J58: By revenue | K58: fines | L58: The total value of fines, settlements and other financial penalties related to social factors issued to the company/group by UK and US regulators over the past three years. | M58: Count | N58: Numeric | O58: Violation Tracker US/UK | P58: Programmatic | Q58: Scrape | S58: 0 | V58: -1 | W58: -1
A59: Value of Fines Relating to 'People' | B59: Justice | C59: J007 | D59: 59 | E59: justice_fines_people_value_revenue | F59: 1 | G59: 0 | H59: 0 | I59: Any fines that were announced up to three years before the Data of the most recent update of the Responsibility 100 are counted as part of this total. It concerns all fines relating to the 'people' (e.g. human rights, modern slavery, etc). Write down all the fines in the flag column & add them up. Then calculate it as a percentage of total revenue. If it is not in GBP, take the average currecy conversion over the reporting period, or Jan-Jan if no reporting period using this tool https://docs.google.com/spreadsheets/d/1pFxv18Kp2d0EmS6BA4wrlqL_gsbwE8W0h-FLYPWFFog/edit#gid=0 | J59: By revenue | K59: fines | L59: The total value of fines, settlements and other financial penalties related to social factors issued to the company/group by UK and US regulators over the past three years as a proportion of total revenue reported by the company/group in the most recently reported year. | M59: GBP | N59: Numeric | O59: Violation Tracker US/UK | P59: Programmatic | Q59: Scrape | V59: -1 | W59: -1
A60: Value of Fines Relating to 'Planet' | B60: Justice | C60: J009 | D60: 61 | E60: justice_fines_planet_value_revenue | F60: 1 | G60: 0 | H60: 0 | I60: Any fines that were announced up to three years before the Data of the most recent update of the Responsibility 100 are counted as part of this total. It concerns all fines relating to the 'planet' (e.g. environment). Write down all the fines in the flag column & add them up. Then calculate it as a percentage of total revenue.If it is not in GBP, take the average currecy conversion over the reporting period, or Jan-Jan if no reporting period using this tool https://docs.google.com/spreadsheets/d/1pFxv18Kp2d0EmS6BA4wrlqL_gsbwE8W0h-FLYPWFFog/edit#gid=0 | J60: By revenue | K60: fines, environmental fines | L60: The total value of fines, settlements and other financial penalties related to environmental factors issued to the company/group by UK and US regulators over the past three years as a proportion of total revenue reported by the company/group in the most recently reported year. | M60: GBP | N60: Numeric | O60: Violation Tracker US/UK | P60: Programmatic | Q60: Scrape | V60: -1 | W60: -1
A61: Total Number of Accusations of Human Rights Violations Not Responded To | B61: Justice | C61: J003 | D61: 62 | E61: justice_accusations_response | F61: 1 | G61: 1 | H61: 0 | I61: Human Rights accusations that were levied on the BHRRC's website (https://www.business-humanrights.org/en/) up to three years before the Data of the update are counted. Companies are responsible at which an accusation is made or tribunal is brought. When a company buys a subsidiary, they take on responsibility for accusations. When they sell it, they sell the responsibility, too. This is because companies are expected to conduct due diligence in mergers and acquisitions, and so should know of the risk of human rights accusations or tribunals. This is based on the UN Guiding Principles. | J61: None | K61: human rights, violations, fines | L61: The absolute number of human rights accusations, compiled by the Business and Human Rights Resource Centre (made over the past three years), that have not been replied to by the company. If the company has received no human rights accusations, this value appears as N/A. | M61: Count | N61: Numeric | O61: BHRRC https://www.business-humanrights.org/ | P61: Additional Indicators | S61: 0 | V61: -1 | W61: -1
A62: Number of Whistleblowing Cases Reported | B62: Justice | C62: J030 | D62: 63 | E62: whistleblowing_cases | I62: A whistleblower is a person, usually an employee, who exposes information or activity within a private or public organisation that is deemed illegal, immoral or illicit. This indicator measures the number of whistleblowing cases for each company. Firstly, check annual reports (which can be found on companies House or on the companies website). Check their sustainability / responsible sourcing reports as well. Check also their news section on the website, and do a general Google. | J62: By employees | K62: whistleblowing | L62: A whistleblower is a person, usually an employee, who exposes information or activity within a private or public organisation that is deemed illegal, immoral or illicit. This indicator measures the number of whistleblowing cases for each company. | M62: Count | O62: Annual Report, Modern Slavery Report | P62: Annual Report
A63: Number of Employment Tribunal Cases Upheld | B63: Justice | C63: J010 | D63: 64 | E63: justice_et_upheld | F63: 1 | G63: 1 | H63: 0 | I63: Employment tribunal decisions that took place up to three years before the Data of the update of the Responsibility 100 are counted. The Data of the decisions are given on the gov.uk website. | J63: By employees | K63: tribunal cases, workplace | L63: The number of UK Employment Tribunal cases over the past three years involving the company which saw the Tribunal uphold at least one of the claims of the employee/former employee. | M63: Count | N63: Numeric | O63: UK Employment Tribunal: https://www.gov.uk/employment-tribunal-decisions | P63: Programmatic | Q63: Scrape | S63: 0 | V63: -1 | W63: -1
A64: Membership of an Organisation Promoting Women in STEM | B64: Membership | C64: T114 | D64: 66 | E64: membership_women_stem | F64: 1 | G64: 1 | H64: 0 | I64: Organisations included: WISE, Society of Women Engineers (SWE), AnitaB.org, National Center for Women & Information Technology (NCWIT), Women in Technology International (WITI), Association for Women in Science (AWIS) | J64: None | K64: WISE, women in stem, women, inclusive | L64: This indicator is a binary variable indicating whether a company has signed up as an organisation to an inititative promoting women in STEM. | M64: 1/0 | N64: Binary | O64: WISE Campaign https://www.wisecampaign.org.uk/ | P64: Programmatic | Q64: Scrape | S64: 0 | V64: 1 | W64: 1
A65: Membership of an Organisation Promoting Renewable Energy Adoption | B65: Membership | C65: T115 | D65: 67 | E65: membership_renewables | F65: 1 | G65: 1 | H65: 1 | I65: Organisations included: The Climate Group (which includes access to initiatives such as RE100, EV100, and EP100), Renewable Energy Buyers Alliance (REBA) | J65: None | K65: RE100, EV100, EP100, Climate Group, renewables, | L65: This indicator is a binary variable indicating whether a company has signed up as an organisation to an inititative promoting renewably energy adoption. | M65: 1/0 | N65: Binary | O65: RE100 http://there100.org/ | P65: Additional Indicators | Q65: might be able to scrape | V65: 1 | W65: 1
A66: Membership of an Organisation Promoting Social Responsibility | B66: Membership | C66: T116 | D66: 68 | E66: membership_supply_chains | F66: 1 | G66: 1 | H66: 1 | I66: Organisations included: Social Accountability International (SAI), Responsible Business Alliance (RBA) No requirements: Social Value International (SVI), Business for Social Responsibility (BSR) | J66: None | K66: Social Accountability International, SAI, Responsible Business Alliance, RBA, Social Value International, SVI, supply chains, social | L66: This indicator is a binary variable indicating whether a company has signed up as an organisation to an organisation promoting social responsibility. | M66: 1/0 | N66: Binary | O66: UN Global Compact | P66: Additional Indicators | Q66: might be able to scrape | V66: 1 | W66: 1
A67: Membership of Reporting Initiative | B67: Membership | C67: T117 | D67: 68 | E67: membership_reporting | I67: Organisations included: CDP, Global Reporting Initiative (GRI) | K67: CDP, GRI, reporting | L67: This indicator is a binary variable indicating whether a company has signed up as an organisation to a reporting initiative.
A68: Membership of an Organisation Promoting Sustainable Business | B68: Membership | C68: T118 | D68: 69 | E68: membership_sustainability_org | F68: 1 | G68: 1 | H68: 1 | I68: Organisations included: Ceres, No requirements: The World Business Council for Sustainable Development (WBCSD), UN Global Compact | J68: None | K68: ICRS, organisation, Ceres, Business for Social Responsibility, BSR, The World Business Council for Sustainable Development, WBCSD, UNGC, UN Global Compact | L68: This indicator is a binary variable indicating whether a company has signed up as an organisation to an inititative promoting sustainable business. | M68: 1/0 | N68: Binary | O68: ICRS | P68: Additional Indicators | V68: 1 | W68: 1
A69: Company is a Signatory of the Race at Work Charter | B69: Membership | C69: T020 | D69: 70 | E69: talk_race_work | F69: 1 | G69: 1 | H69: 0 | I69: Find whether the company is a signatory on this website here: https://www.bitc.org.uk/race-at-work-charter-signatories/ | J69: None | K69: race at work charter | L69: A binary indicator company is a signatory of the Business in the Community's Race at Work Charter. The Race at Work Charter outlines seven key actions to improve the quality of opportunity in the workplace, such as capturing ethnicity data and publicise progress made. | M69: 1/0 | N69: Binary | O69: Race at Work Charter | P69: Programmatic | Q69: Scrape
A70: Company is a Signatory of the Prompt Payment Code | B70: Membership | C70: W002 | D70: 71 | E70: wb_ppc_signatory | F70: 1 | G70: 1 | H70: 0 | I70: Check the Prompt Payment Code website. Companies receive 2 points if they are active signatories, 1 point if temporarily suspended, or 0 points if they are not signatories | J70: None | K70: prompt payment code | L70: A variable indicating a company's level of participation in the Prompt Payment Code. 0 indicates a company does not participate, 1 indicates the company has participated but since been suspended from the Code; 2 means the company is an active signatory of the Code. | M70: 2/1/0 | N70: Categorical | O70: BEIS Prompt Payment Code | P70: Programmatic | Q70: Scrape | S70: 0 | U70: Square Transform | V70: 1 | W70: 1
A71: Total Number of Employees (FTE) | B71: Misc | C71: M001 | D71: 72 | E71: misc_employees | G71: 1 | H71: 0 | I71: Find total number of full-time equivalent (FTE) employees (if possible). If not, use any total / average employee count for that reporting period. Write down any notes in the flag column, | J71: None | K71: employees | L71: The total number of people (Full-Time Equivalent, FTE) employed by a company/group in the most recently reported year. | M71: Count | N71: Numeric | O71: Annual Report | P71: Annual Report | T71: Ignore | V71: 1
A72: Total Number of Employees (FTE) in Previous Year | B72: Misc | C72: M002 | D72: 73 | E72: misc_employees_previous | G72: 1 | H72: 0 | I72: Find total number of full-time equivalent (FTE) employees in the previous year if possible. If not, use any total / average employee count for that reporting period. | J72: None | K72: employees | L72: The total number of people (Full-Time Equivalent, FTE) employed by a company/group in the previously reported year. | M72: Count | N72: Numeric | O72: Annual Report | P72: Annual Report | T72: Ignore | V72: 1
A73: Number of UK employees | B73: Misc | C73: M009 | D73: 74 | E73: misc_employees_uk | I73: Find total number of full-time equivalent (FTE) employees in the UK if possible. If not, use any total / average employee count | J73: None | L73: The total number of people (Full-Time Equivalent, FTE) employed by a company/group in the most recently reported year in the UK. | M73: Count | N73: Numeric | O73: Annual Report | P73: Annual Report
A74: Value of Market Capitalisation | B74: Misc | C74: M003 | D74: 75 | E74: misc_cap | G74: 0 | H74: 0 | I74: This number can be found in annual report or London Stock Exchange If it is not in GBP, take the average currecy conversion over the reporting period, or Jan-Jan if no reporting period using this tool https://docs.google.com/spreadsheets/d/1pFxv18Kp2d0EmS6BA4wrlqL_gsbwE8W0h-FLYPWFFog/edit#gid=0 | J74: None | L74: The market capitalisation of a company. This will most likely be disclosed alongside CEO pay in 'Remuneration' section of Annual Report. Use this converter to do a currency conversion over the dates of the AR (ideally using moneths, but do Jan-Jan if none available) https://docs.google.com/spreadsheets/d/1pFxv18Kp2d0EmS6BA4wrlqL_gsbwE8W0h-FLYPWFFog/edit#gid=0 | M74: GBP | N74: Numeric | O74: London Stock Exchange | P74: Programmatic | Q74: Try to scrape. If not, change to Annual Report, and add 1 in AR column | T74: Ignore | V74: 1
A75: Annual Report Release Date | B75: Misc | C75: M006 | D75: 76 | E75: misc_annual_date | G75: 0 | H75: 0 | I75: Please find the year (or exact Data if available) that the report was published | J75: None | L75: Year of publication of the annual report. | M75: Data | N75: Text | O75: Annual report or company website | P75: Annual Report | T75: Ignore | V75: 1
A76: Annual Report URL | B76: Misc | C76: M007 | D76: 77 | E76: misc_annual_link | G76: 0 | H76: 0 | I76: Write down the annual report URL | J76: None | L76: The URL to the company's most recent annual report. | M76: URL | N76: Text | O76: Company Website | P76: Annual Report | T76: Ignore | V76: 1
A77: Sustainability Report URL | B77: Misc | C77: M008 | D77: 78 | E77: misc_sustainability_link | G77: 0 | H77: 0 | I77: Write down the sustainability report URL | J77: None | L77: The URL to the company's most recent sustainability report. | M77: URL | N77: Text | O77: Company Website | P77: Annual Report | T77: Ignore | V77: 1
A78: Total Number of Graduates Accepted | B78: Skills and Education | C78: S001 | D78: 79 | E78: collection_grads | I78: This is specifically the count of new graduates each year, ie. Graduate programme intake, rather than the total number of graduates at the company. | J78: None | K78: graduates, graduate scheme | L78: The total number of graduates hired each year. | M78: Count | N78: Numeric | O78: Annual Report | P78: Annual Report
A79: Total Number of Apprentices Accepted | B79: Skills and Education | C79: S002 | D79: 79 | E79: collection_apprentices | F79: 1 | G79: 1 | H79: 0 | I79: This is specifically the count of new apprentices each year, ie. Graduate programme intake, rather than the total number of graduates at the company. | J79: None | K79: apprenticeships, apprentices, apprenticeship scheme | L79: The total number of apprentices hired each year. | M79: Count | N79: Numeric | O79: Annual Report | P79: Annual Report | S79: 0 | V79: 1 | W79: 1
A80: Total Number of Graduates Accepted as a Proportion of Total Employees (%) | B80: Skills and Education | C80: S003 | D80: 80 | E80: skills_training_grads | I80: Total Number of Graduates Accepted / Employees | J80: By employees | L80: The percentage of total employees reported as graduates. | M80: % | N80: Numeric | O80: Annual Report | P80: Programmatic | Q80: Scale
A81: Total Number of Apprentices Accepted as a Proportion of Total Employees (%) | B81: Skills and Education | C81: S004 | D81: 80 | E81: skills_training_apprentices | I81: Total Number of Apprentices Accepted / Employees | J81: By employees | L81: The percentage of total employees reported as apprentices. | M81: % | N81: Numeric | O81: Annual Report | P81: Programmatic | Q81: Scale
A82: % Employees Receiving Training | B82: Skills and Education | C82: S006 | D82: 81 | E82: skills_training_employees_pct | F82: 1 | G82: 0 | H82: 0 | I82: Only collect if company provides as a total; do not try to calculate yourself; do not include mandatory training (e.g. health and safety training). | J82: By employees | K82: training, learning and development | L82: The number of total employees who receive non-mandatory training. | M82: % | N82: Numeric | O82: Annual Report | P82: Annual Report | V82: 1 | W82: 1
A83: Total Number of Employees Receiving Training | B83: Skills and Education | C83: S005 | D83: 81 | E83: skills_training_employees | F83: 1 | G83: 0 | H83: 0 | I83: Only collect if company provides as a total; do not try to calculate yourself; do not include mandatory training (e.g. health and safety training). | J83: None | K83: training, learning and development | L83: The number of total employees who receive non-mandatory training. | M83: Count | N83: Numeric | O83: Annual Report | P83: Annual Report | V83: 1 | W83: 1
A84: Total Investment in Training as a Proportion of Revenue | B84: Skills and Education | C84: S008 | D84: 82 | E84: skills_training_spend_rev | F84: 1 | G84: 1 | H84: 0 | I84: Only collect if company provides as a total; do not try to calculate yourself. If it's not in £ then convert using the average exchange rate for the past three years from this converter. https://docs.google.com/spreadsheets/d/1pFxv18Kp2d0EmS6BA4wrlqL_gsbwE8W0h-FLYPWFFog/edit#gid=0 | J84: By revenue | K84: training, learning and development | L84: The total amount of investment in £ into training by a company/group as a proportion of XXX | M84: % | N84: Numeric | O84: Annual Report | P84: Programmatic | Q84: Scale | S84: 0 | V84: 1 | W84: 1
A85: Total Investment in Training | B85: Skills and Education | C85: S007 | D85: 82 | E85: skills_training_spend | F85: 1 | G85: 1 | H85: 0 | I85: Only collect if company provides as a total; do not try to calculate yourself. If it is not in GBP, take the average currecy conversion over the reporting period, or Jan-Jan if no reporting period using this tool https://docs.google.com/spreadsheets/d/1pFxv18Kp2d0EmS6BA4wrlqL_gsbwE8W0h-FLYPWFFog/edit#gid=0 | J85: None | K85: training, learning and development | L85: The total amount of investment in £ into training by a company/group as a proportion of XXX | M85: GBP | N85: Numeric | O85: Annual Report | P85: Annual Report | S85: 0 | V85: 1 | W85: 1
A86: Ambition Level of Science Based Target Set | B86: Targets | C86: T070 | D86: 83 | E86: talk_target_ambition | F86: 1 | G86: 1 | H86: 0 | I86: This indicator measures the ambition-level of Science Based Targets. Companies score 0 if none are set, 1 if set at 2 degrees, 2 if set at well below 2 degrees or 3 if set at 1.5 degrees. | J86: None | K86: science based target | L86: This indicator measures the ambition-level of Science Based Targets. Companies score 0 if none are set, 1 if set at 2 degrees, 2 if set at well below 2 degrees or 3 if set at 1.5 degrees. | M86: 0/1/2/3 | N86: Categorical | O86: Annual Report | P86: Programmatic | Q86: Scrape
A87: Comprehensiveness Score | B87: Targets | C87: T063 | D87: 84 | E87: talk_target_comp | F87: 1 | H87: 0 | I87: Companies are scored by summing pillar weights for each have a target for. | J87: None | K87: transparency | L87: All ‘Talk’ indicators are assessed to produce a ‘Comprehensiveness Score’ which shows the coverage of all the pillars that a company has included in its targets i.e. a company that has set targets relating to each of the pillars receives the highest possible ‘Comprehensiveness Score’. | N87: Numeric | O87: Bespoke | P87: Programmatic | Q87: Add methodology please! | V87: 1
A88: Number of Targets relating to Climate | B88: Targets | C88: T106 | D88: 85 | E88: talk_target_climate_count | G88: 0 | H88: 1 | I88: This will be available in annual reports or sustainability reports. Count up the targets & provide all sources. | J88: None | K88: targets, aim, by 20, goal | L88: This indicator counts the number of time-bound and measurable targets relating to climate. See annex for full text of targets. | M88: Count | N88: Numeric | O88: Annual Report | P88: Targets | T88: Ignore
A89: Number of Targets relating to Equality | B89: Targets | C89: T107 | D89: 86 | E89: talk_target_equality_count | G89: 0 | H89: 0 | I89: This will be available in annual reports or sustainability reports. Count up the targets & provide all sources. | J89: None | K89: targets, aim, by 20, goal | L89: This indicator counts the number of time-bound and measurable targets relating to equality. See annex for full text of targets. | M89: Count | N89: Numeric | O89: Annual Report | P89: Targets | T89: Ignore
A90: Number of Targets relating to Poverty and Wellbeing | B90: Targets | C90: T108 | D90: 87 | E90: talk_target_pov_count | G90: 0 | H90: 0 | I90: This will be available in annual reports or sustainability reports. Count up the targets & provide all sources. | J90: None | K90: targets, aim, by 20, goal | L90: This indicator counts the number of time-bound and measurable targets relating to poverty and wellbeing. See annex for full text of targets. | M90: Count | N90: Numeric | O90: Annual Report | P90: Targets | T90: Ignore
A91: Number of Targets relating to Justice | B91: Targets | C91: T109 | D91: 88 | E91: talk_target_justice_count | G91: 0 | H91: 0 | I91: This will be available in annual reports or sustainability reports. Count up the targets & provide all sources. | J91: None | K91: targets, aim, by 20, goal | L91: This indicator counts the number of time-bound and measurable targets relating to justice. See annex for full text of targets. | M91: Count | N91: Numeric | O91: Annual Report | P91: Targets | T91: Ignore
A92: Number of Targets relating to Skills | B92: Targets | C92: T110 | D92: 89 | E92: talk_target_skills_count | G92: 0 | H92: 0 | I92: This will be available in annual reports or sustainability reports. Count up the targets & provide all sources. | J92: None | K92: targets, aim, by 20, goal | L92: This indicator counts the number of time-bound and measurable targets relating to skills. See annex for full text of targets. | M92: Count | N92: Numeric | O92: Annual Report | P92: Targets | T92: Ignore
A93: Number of Targets relating to Good Business | B93: Targets | C93: T111 | D93: 90 | E93: talk_target_bus_count | G93: 0 | H93: 0 | I93: This will be available in annual reports or sustainability reports. Count up the targets & provide all sources. | J93: None | K93: targets, aim, by 20, goal | L93: This indicator counts the number of time-bound and measurable targets relating to good business. See annex for full text of targets. | M93: Count | N93: Numeric | O93: Annual Report | P93: Targets | T93: Ignore
A94: Net Zero Target Ambition | B94: Targets | C94: T113 | D94: 91 | E94: talk_target_netzero_date | F94: 1 | G94: 1 | H94: 1 | I94: Date by which the company has set a time-bound target to achieve Net Zero across their operations. This must be across all operations at the minimum. | J94: None | K94: net zero | L94: Data by which company aims to achieve Net Zero (Year). | M94: Year | N94: Text | O94: Annual Report | P94: Targets | W94: 1
A95: Company is a Living Wage Provider Accredited Organisation | B95: Poverty and Wellbeing | C95: W001 | D95: 92 | E95: wb_living_wage | F95: 1 | G95: 1 | H95: 0 | I95: Go to Living Wage Foundation website https://www.livingwage.org.uk/ and see if they are a member. Alternatively, see if they mention it in the annual report. | J95: None | K95: living wage, living wage accredited, living wage foundation | L95: A binary variable indicating whether a company is an accredited living wage provider or not. | M95: 1/0 | N95: Binary | O95: Living Wage Foundation https://www.livingwage.org.uk/ | P95: Additional Indicators | Q95: Scrape | S95: 0 | V95: 1 | W95: 1
A96: Company does provide Healthcare Services for Employees | B96: Poverty and Wellbeing | C96: W007 | D96: 93 | E96: wb_healthcare | F96: 1 | G96: 1 | H96: 0 | I96: Find this fact in the annual report - potentially under employees/wellbeing section. | J96: None | K96: healthcare, private healthcare, mental health | L96: A binary indicator showing whether or not the company/group provides healthcare e.g. on-site GP practices, free consultations or treatment, to all employees. | M96: 1/0 | N96: Binary | O96: Annual reports/Company benefits | P96: Annual Report | S96: 0 | V96: 1 | W96: 1
A97: Company Publishes List of Suppliers (None / Tier 1 / Tier 2 and Above) | B97: Poverty and Wellbeing | C97: J028 | D97: 94 | E97: slav_tier1_suppliers | F97: 1 | G97: 1 | H97: 0 | I97: Check for a list or map of suppliers (or link to either). Can be worth googling for this one outside of the Modern Slavery Report (quite exceptional). Input 0 for none, 1 for all Tier 1 (direct) suppliers, 2 for all Tier 2 suppliers and above Keywords: list of, full, Tier 1, map, sourcing map | J97: None | K97: suppliers, tier 1, direct, indirect, tier 2, map, list | L97: This is a binary indicator to record whether a company publishes a list of suppliers that the they conducts business with, including contracted manufacturing facilities or production partners: none - 0, Tier 1 - 1, Tier 2 and above - 2. | M97: 0/1/2 | N97: Categorical | O97: Modern Slavery Statement | P97: Annual Report | S97: 0 | V97: 1 | W97: 1
A98: % Supply Chains or Suppliers Subjected to Risk-Assessment | B98: Poverty and Wellbeing | C98: J023 | D98: 95 | E98: slav_chains | G98: 1 | H98: 0 | I98: This will be found in the annual report and/or on their website | J98: None | K98: supply chains, supplier, risk, risk assessment, human rights, slavery, modern slavery | L98: The percentage of supply chains that the company has subjected to risk-assessment according to its Modern Slavery Statement. | M98: Percentage | N98: Numeric | O98: Modern Slavery Statement | P98: Annual Report
A99: % Supplier Payments Made Within Agreed Terms | B99: Poverty and Wellbeing | C99: W004 | D99: 96 | E99: wb_ppc_agreed | F99: 1 | G99: 1 | H99: 0 | I99: Uses Duty to Report Data (https://www.gov.uk/check-when-businesses-pay-invoices), paired with our Data on all subsidiaries to find and average prompt payment Data across all company subsidiaries. Take mean average. | J99: None | K99: supplier payments | L99: This indicator records whether a company is a Signatory of the Prompt Payment Code, a voluntary scheme designed to encourage prompt payment between businesses, particularly from larger to smaller businesses. | M99: Percentage | N99: Numeric | O99: Duty to Report https://check-payment-practices.service.gov.uk/search | P99: Programmatic | Q99: Scrape | S99: 0 | V99: 1 | W99: 1
A100: % Supplier Payments In Less than 30 Days | B100: Poverty and Wellbeing | C100: W005 | D100: 97 | E100: wb_ppc_30 | F100: 1 | G100: 1 | H100: 0 | I100: Uses Duty to Report Data (https://www.gov.uk/check-when-businesses-pay-invoices) paired with our Data on all subsidiaries to find and average prompt payment Data across all company subsidiaries. Use the mean. | J100: None | K100: supplier payments | L100: This indicator records the % of supplier payments made within their agreed terms (%). | M100: Percentage | N100: Numeric | O100: Duty to Report https://check-payment-practices.service.gov.uk/search | P100: Programmatic | Q100: Scrape | S100: 0 | V100: 1 | W100: 1
...

Sheet company_info
A1: ticker | B1: company_name | C1: yahoo_name | D1: website_ticker | E1: yahoo_ticker | F1: sector | G1: industry | H1: company_description | I1: companies_house_id | J1: companies_house_link | K1: search_terms | L1: violation_tracker_name | M1: glassdoor_url
A2: AAF | B2: Airtel Africa | C2: {=xlookup(B2, sectors!A:A, sectors!A:A)} -> Airtel Africa | D2: =left(E2, 3) -> AAF | E2: AAF.L | F2: {=xlookup(A2, sectors!B:B, sectors!C:C)} -> Retail & Services | G2: {=XLOOKUP(A2, sectors!B:B, sectors!E:E)} -> Telecommunications | H2: Airtel Africa is a multinational company that provides telecommunications and mobile money services in 14 countries in Africa, primarily in East, Central and West Africa. Airtel Africa is majority owned by the Indian telecommunications company Bharti Airtel. | I2: 11462215 | J2: ="https://find-and-update.company-information.service.gov.uk/company/"&$I2 -> https://find-and-update.company-information.service.gov.uk/company/11462215 | K2: airtel | M2: https://www.glassdoor.co.uk/Overview/Working-at-Bharti-Airtel-EI_IE38320.11,24.htm
A3: AAL | B3: Anglo American | C3: Anglo American plc | D3: =left(E3, 3) -> AAL | E3: AAL.L | F3: {=xlookup(A3, sectors!B:B, sectors!C:C)} -> Mining & Extraction | G3: {=XLOOKUP(A3, sectors!B:B, sectors!E:E)} -> Mining | H3: Anglo American is a multinational mining company that is the world's largest producer of platinum, with around 40% of world output, as well as being a major producer of diamonds, copper, nickel, iron ore, polyhalite and steelmaking coal. | I3: 03564138 | J3: ="https://find-and-update.company-information.service.gov.uk/company/"&$I3 -> https://find-and-update.company-information.service.gov.uk/company/03564138 | K3: anglo american | L3: Anglo American PLC | M3: https://www.glassdoor.co.uk/Overview/Working-at-Anglo-American-EI_IE3491.11,25.htm
A4: ABDN | B4: Abrdn | C4: {=xlookup(B4, sectors!A:A, sectors!A:A)} -> Abrdn | D4: =left(E4, 3) -> ABD | E4: ABDN.L | F4: {=xlookup(A4, sectors!B:B, sectors!C:C)} -> Financial Services | G4: {=XLOOKUP(A4, sectors!B:B, sectors!E:E)} -> Financial Services | H4: Abrdn is an investment management group, managing assets for both institutions and private investors from offices around the world. | I4: SC286832 | J4: ="https://find-and-update.company-information.service.gov.uk/company/"&$I4 -> https://find-and-update.company-information.service.gov.uk/company/SC286832 | K4: abrdn | L4: Abrdn PLC | M4: https://www.glassdoor.co.uk/Overview/Working-at-abrdn-EI_IE10239.11,16.htm
A5: ABF | B5: Associated British Foods | C5: {=xlookup(B5, sectors!A:A, sectors!A:A)} -> Associated British Foods | D5: =left(E5, 3) -> ABF | E5: ABF.L | F5: {=xlookup(A5, sectors!B:B, sectors!C:C)} -> Food & Beverage | G5: {=XLOOKUP(A5, sectors!B:B, sectors!E:E)} -> Food Producers | H5: Associated British Foods plc is a multinational food processing and retailing company. Its ingredients division is the world's second-largest producer of both sugar and baker's yeast and a major producer of other ingredients including emulsifiers, enzymes and lactose. | I5: 00293262 | J5: ="https://find-and-update.company-information.service.gov.uk/company/"&$I5 -> https://find-and-update.company-information.service.gov.uk/company/00293262 | K5: associated british foods, primark, allied bakeries | L5: Associated British Foods | M5: https://www.glassdoor.co.uk/Overview/Working-at-Associated-British-Foods-EI_IE10110.11,35.htm
A6: ADM | B6: Admiral Group | C6: {=xlookup(B6, sectors!A:A, sectors!A:A)} -> Admiral Group | D6: =left(E6, 3) -> ADM | E6: ADM.L | F6: {=xlookup(A6, sectors!B:B, sectors!C:C)} -> Financial Services | G6: {=XLOOKUP(A6, sectors!B:B, sectors!E:E)} -> Non-life Insurance | H6: Admiral Group plc is a global financial services company offering insurance products, including motor, household, travel and pet insurance, and personal lending products. | I6: 03849958 | J6: ="https://find-and-update.company-information.service.gov.uk/company/"&$I6 -> https://find-and-update.company-information.service.gov.uk/company/03849958 | K6: admiral | L6: Admiral Group | M6: https://www.glassdoor.co.uk/Overview/Working-at-Admiral-Group-EI_IE35772.11,24.htm
A7: AHT | B7: Ashtead Group | C7: {=xlookup(B7, sectors!A:A, sectors!A:A)} -> Ashtead Group | D7: =left(E7, 3) -> AHT | E7: AHT.L | F7: {=xlookup(A7, sectors!B:B, sectors!C:C)} -> Retail & Services | G7: {=XLOOKUP(A7, sectors!B:B, sectors!E:E)} -> Support Services | H7: Ashtead Group is an international equipment rental company with national networks in the US, UK and Canada, trading under the name Sunbelt Rentals. | I7: 01807982 | J7: ="https://find-and-update.company-information.service.gov.uk/company/"&$I7 -> https://find-and-update.company-information.service.gov.uk/company/01807982 | K7: ashtead | L7: Ashtead Group PLC | M7: https://www.glassdoor.co.uk/Reviews/Sunbelt-Rentals-Reviews-E19665.htm
A8: ANTO | B8: Antofagasta | C8: Antofagasta plc | D8: ANTO | E8: ANTO.L | F8: {=xlookup(A8, sectors!B:B, sectors!C:C)} -> Mining & Extraction | G8: {=XLOOKUP(A8, sectors!B:B, sectors!E:E)} -> Mining | H8: Antofagasta Plc is a Chilean multinational company, which engages in copper mining, transport, and water distribution businesses. | I8: 01627889 | J8: ="https://find-and-update.company-information.service.gov.uk/company/"&$I8 -> https://find-and-update.company-information.service.gov.uk/company/01627889 | K8: antofagasta | M8: https://www.glassdoor.co.uk/Overview/Working-at-Antofagasta-EI_IE11472.11,22.htm
A9: AUTO | B9: Auto Trader Group | C9: {=xlookup(B9, sectors!A:A, sectors!A:A)} -> Auto Trader Group | D9: AUTO | E9: AUTO.L | F9: {=xlookup(A9, sectors!B:B, sectors!C:C)} -> Retail & Services | G9: {=XLOOKUP(A9, sectors!B:B, sectors!E:E)} -> Media | H9: Auto Trader Group is a British automotive online marketplace and classified advertising business. It enables the buying and selling of new and used vehicles by private sellers and trade retailers. | I9: 09439967 | J9: ="https://find-and-update.company-information.service.gov.uk/company/"&$I9 -> https://find-and-update.company-information.service.gov.uk/company/09439967 | K9: auto trader | M9: https://www.glassdoor.co.uk/Overview/Working-at-Auto-Trader-UK-EI_IE505215.11,25.htm
A10: AV. | B10: Aviva | C10: {=xlookup(B10, sectors!A:A, sectors!A:A)} -> Aviva | D10: =left(E10, 3) -> AV. | E10: AV.L | F10: {=xlookup(A10, sectors!B:B, sectors!C:C)} -> Financial Services | G10: {=XLOOKUP(A10, sectors!B:B, sectors!E:E)} -> Life Insurance | H10: Aviva is a British multinational insurance company with 18 million customers across its core markets of the United Kingdom, Ireland and Canada. In the United Kingdom, Aviva is the largest general insurer and a leading life and pensions provider. | I10: 02468686 | J10: ="https://find-and-update.company-information.service.gov.uk/company/"&$I10 -> https://find-and-update.company-information.service.gov.uk/company/02468686 | K10: aviva | M10: https://www.glassdoor.co.uk/Overview/Working-at-Aviva-EI_IE311641.11,16.htm
A11: AZN | B11: Astrazeneca | C11: {=xlookup(B11, sectors!A:A, sectors!A:A)} -> AstraZeneca | D11: =left(E11, 3) -> AZN | E11: AZN.L | F11: {=xlookup(A11, sectors!B:B, sectors!C:C)} -> Healthcare & Pharmaceutical | G11: {=XLOOKUP(A11, sectors!B:B, sectors!E:E)} -> Pharmaceuticals & Biotechnology | H11: AstraZeneca is a British-Swedish multinational pharmaceutical and biotechnology company with its headquarters in Cambridge, England. | I11: 02723534 | J11: ="https://find-and-update.company-information.service.gov.uk/company/"&$I11 -> https://find-and-update.company-information.service.gov.uk/company/02723534 | K11: astrazeneca | L11: AstraZeneca | M11: https://www.glassdoor.co.uk/Overview/Working-at-AstraZeneca-EI_IE9214.11,22.htm
A12: BA. | B12: BAE Systems | C12: {=xlookup(B12, sectors!A:A, sectors!A:A)} -> BAE Systems | D12: =left(E12, 3) -> BA. | E12: BA.L | F12: {=xlookup(A12, sectors!B:B, sectors!C:C)} -> Engineering & Construction | G12: {=XLOOKUP(A12, sectors!B:B, sectors!E:E)} -> Aerospace & Defence | H12: BAE Systems is a British multinational arms, security, and aerospace company based in London, England. It is the largest defence contractor in Europe, and ranked the seventh-largest in the world based. | I12: 01470151 | J12: ="https://find-and-update.company-information.service.gov.uk/company/"&$I12 -> https://find-and-update.company-information.service.gov.uk/company/01470151 | K12: bae systems | L12: BAE Systems | M12: https://www.glassdoor.co.uk/Overview/Working-at-BAE-Systems-EI_IE1653490.11,22.htm
A13: BARC | B13: Barclays | C13: {=xlookup(B13, sectors!A:A, sectors!A:A)} -> Barclays | D13: BARC | E13: BARC.L | F13: {=xlookup(A13, sectors!B:B, sectors!C:C)} -> Financial Services | G13: {=XLOOKUP(A13, sectors!B:B, sectors!E:E)} -> Banks | H13: Barclays is a British multinational universal bank, providing consumer banking services, as well as being a global corporate and investment bank. | I13: 00048839 | J13: ="https://find-and-update.company-information.service.gov.uk/company/"&$I13 -> https://find-and-update.company-information.service.gov.uk/company/00048839 | K13: barclays | L13: Barclays | M13: https://www.glassdoor.co.uk/Overview/Working-at-Barclays-EI_IE3456.11,19.htm
A14: BATS | B14: British American Tobacco | C14: {=xlookup(B14, sectors!A:A, sectors!A:A)} -> British American Tobacco | D14: BATS | E14: BATS.L | F14: {=xlookup(A14, sectors!B:B, sectors!C:C)} -> Tobacco | G14: {=XLOOKUP(A14, sectors!B:B, sectors!E:E)} -> Tobacco | H14: British American Tobacco is a British multinational company that manufactures and sells cigarettes, tobacco and other nicotine products. | I14: 03407696 | J14: ="https://find-and-update.company-information.service.gov.uk/company/"&$I14 -> https://find-and-update.company-information.service.gov.uk/company/03407696 | K14: british american tobacco | L14: British American Tobacco | M14: https://www.glassdoor.co.uk/Overview/Working-at-British-American-Tobacco-EI_IE8378.11,35.htm
A15: BDEV | B15: Barratt Developments | C15: {=xlookup(B15, sectors!A:A, sectors!A:A)} -> Barratt Developments | D15: BDEV | E15: BDEV.L | F15: {=xlookup(A15, sectors!B:B, sectors!C:C)} -> Engineering & Construction | G15: {=XLOOKUP(A15, sectors!B:B, sectors!E:E)} -> Household Goods & Home Construction | H15: Barratt Developments is one of the largest residential property development and construction companies in the United Kingdom operating across England, Wales and Scotland. | I15: 00604574 | J15: ="https://find-and-update.company-information.service.gov.uk/company/"&$I15 -> https://find-and-update.company-information.service.gov.uk/company/00604574 | K15: barratt developments | M15: https://www.glassdoor.co.uk/Overview/Working-at-Barratt-Developments-EI_IE10844.11,31.htm
A16: BEZ | B16: Beazley | C16: Beazley Group | D16: =left(E16, 3) -> BEZ | E16: BEZ.L | F16: {=xlookup(A16, sectors!B:B, sectors!C:C)} -> Financial Services | G16: {=XLOOKUP(A16, sectors!B:B, sectors!E:E)} -> Insurance | H16: Beazley is the British parent company of specialist insurance businesses with operations in Europe, the US, and Asia. it is a Lloyds of London insurer, specialising in writing specialty-risk insurance and reinsurance business. | I16: 09763575 | J16: ="https://find-and-update.company-information.service.gov.uk/company/"&$I16 -> https://find-and-update.company-information.service.gov.uk/company/09763575 | K16: beazley | M16: https://www.glassdoor.co.uk/Overview/Working-at-Beazley-Group-EI_IE24586.11,24.htm
A17: BKG | B17: Berkeley Group Holdings | C17: {=xlookup(B17, sectors!A:A, sectors!A:A)} -> Berkeley Group Holdings | D17: =left(E17, 3) -> BKG | E17: BKG.L | F17: {=xlookup(A17, sectors!B:B, sectors!C:C)} -> Engineering & Construction | G17: {=XLOOKUP(A17, sectors!B:B, sectors!E:E)} -> Household Goods & Home Construction | H17: Berkeley Group Holdings is a British property developer and house-builder based in Cobham, England. | I17: 05172586 | J17: ="https://find-and-update.company-information.service.gov.uk/company/"&$I17 -> https://find-and-update.company-information.service.gov.uk/company/05172586 | K17: berkeley group | M17: https://www.glassdoor.co.uk/Overview/Working-at-Berkeley-Group-EI_IE10118.11,25.htm
A18: BLND | B18: British Land Co | C18: British Land | D18: BLND | E18: BLND.L | F18: {=xlookup(A18, sectors!B:B, sectors!C:C)} -> Real Estate | G18: {=XLOOKUP(A18, sectors!B:B, sectors!E:E)} -> Real Estate Investment Trusts | H18: British Land is a property company which creates, owns and manages UK real estate. It is one of the largest property development and investment companies in the United Kingdom. | I18: 00621920 | J18: ="https://find-and-update.company-information.service.gov.uk/company/"&$I18 -> https://find-and-update.company-information.service.gov.uk/company/00621920 | K18: british land | M18: https://www.glassdoor.co.uk/Overview/Working-at-British-Land-Company-EI_IE10847.11,31.htm
A19: BME | B19: B&M | C19: B&M European Value Retail S.A. | D19: =left(E19, 3) -> BME | E19: BME.L | F19: {=xlookup(A19, sectors!B:B, sectors!C:C)} -> Retail & Services | G19: {=XLOOKUP(A19, sectors!B:B, sectors!E:E)} -> Retailers | H19: B&M is a British multinational variety store chain founded in 1978 and incorporated in Luxembourg. | I19: 08309974 | J19: ="https://find-and-update.company-information.service.gov.uk/company/"&$I19 -> https://find-and-update.company-information.service.gov.uk/company/08309974 | K19: b&m | M19: https://www.glassdoor.co.uk/Overview/Working-at-B-and-M-Retail-EI_IE629657.11,25.htm
A20: BNZL | B20: Bunzl | C20: {=xlookup(B20, sectors!A:A, sectors!A:A)} -> Bunzl | D20: BNZL | E20: BNZL.L | F20: {=xlookup(A20, sectors!B:B, sectors!C:C)} -> Retail & Services | G20: {=XLOOKUP(A20, sectors!B:B, sectors!E:E)} -> Support Services | H20: Bunzl plc is a British multinational distribution and outsourcing company headquartered in London, England. | I20: 00358948 | J20: ="https://find-and-update.company-information.service.gov.uk/company/"&$I20 -> https://find-and-update.company-information.service.gov.uk/company/00358948 | K20: bunzl | M20: https://www.glassdoor.co.uk/Overview/Working-at-Bunzl-EI_IE10133.11,16.htm
A21: BP. | B21: BP | C21: {=xlookup(B21, sectors!A:A, sectors!A:A)} -> BP | D21: =left(E21, 3) -> BP. | E21: BP.L | F21: {=xlookup(A21, sectors!B:B, sectors!C:C)} -> Mining & Extraction | G21: {=XLOOKUP(A21, sectors!B:B, sectors!E:E)} -> Oil & Gas Producers | H21: BP is a British multinational oil and gas company headquartered in London, England. It is one the world's largest companies measured by revenues and profits. | I21: 00102498 | J21: ="https://find-and-update.company-information.service.gov.uk/company/"&$I21 -> https://find-and-update.company-information.service.gov.uk/company/00102498 | K21: bp | L21: BP | M21: https://www.glassdoor.co.uk/Overview/Working-at-BP-EI_IE9011.11,13.htm
A22: BRBY | B22: Burberry | C22: Burberry Group | D22: BRBY | E22: BRBY.L | F22: {=xlookup(A22, sectors!B:B, sectors!C:C)} -> Retail & Services | G22: {=XLOOKUP(A22, sectors!B:B, sectors!E:E)} -> Personal Goods | H22: Burberry Group is a British luxury fashion house that designs and distributes ready to wear, including trench coats, leather accessories, and footwear. | I22: 03458224 | J22: ="https://find-and-update.company-information.service.gov.uk/company/"&$I22 -> https://find-and-update.company-information.service.gov.uk/company/03458224 | K22: burberry | L22: Burberry | M22: https://www.glassdoor.co.uk/Overview/Working-at-Burberry-EI_IE13011.11,19.htm
A23: BT.A | B23: BT Group | C23: {=xlookup(B23, sectors!A:A, sectors!A:A)} -> BT Group | D23: BT.A | E23: BT-A.L | F23: {=xlookup(A23, sectors!B:B, sectors!C:C)} -> Retail & Services | G23: {=XLOOKUP(A23, sectors!B:B, sectors!E:E)} -> Fixed Line Telecommunications | H23: BT Group is a British multinational telecommunications holding company headquartered in London, England. It has operations in around 180 countries and is the largest provider of fixed-line, broadband and mobile services in the UK, and also provides subscription television and IT services. | I23: 04190816 | J23: ="https://find-and-update.company-information.service.gov.uk/company/"&$I23 -> https://find-and-update.company-information.service.gov.uk/company/04190816 | K23: bt, openreach | L23: BT | M23: https://www.glassdoor.co.uk/Overview/Working-at-BT-EI_IE3463.11,13.htm
A24: CCH | B24: Coca-Cola HBC | C24: Coca-Cola Hbc Ag | D24: =left(E24, 3) -> CCH | E24: CCH.L | F24: {=xlookup(A24, sectors!B:B, sectors!C:C)} -> Food & Beverage | G24: {=XLOOKUP(A24, sectors!B:B, sectors!E:E)} -> Beverages | H24: Coca-Cola HBC AG also known as Coca-Cola Hellenic Bottling Company or just Coca-Cola Hellenic is the world's third-largest Coca-Cola anchor bottler in terms of volume with sales of more than 2 billion unit cases. | I24: n/a | K24: coca-cola hbc, coca-cola hellenic | M24: https://www.glassdoor.co.uk/Overview/Working-at-Coca-Cola-HBC-EI_IE10550.11,24.htm
A25: CNA | B25: Centrica | C25: {=xlookup(B25, sectors!A:A, sectors!A:A)} -> Centrica | D25: =left(E25, 3) -> CNA | E25: CNA.L | F25: {=xlookup(A25, sectors!B:B, sectors!C:C)} -> Engineering & Construction | G25: {=XLOOKUP(A25, sectors!B:B, sectors!E:E)} -> Utilities | H25: Centrica plc is a British multinational energy and services company. Its principal activity is the supply of electricity and gas to consumers in the United Kingdom and Ireland. | I25: 03033654 | J25: ="https://find-and-update.company-information.service.gov.uk/company/"&$I25 -> https://find-and-update.company-information.service.gov.uk/company/03033654 | K25: centrica | M25: https://www.glassdoor.co.uk/Overview/Working-at-Centrica-EI_IE6731.11,19.htm
A26: CPG | B26: Compass Group | C26: {=xlookup(B26, sectors!A:A, sectors!A:A)} -> Compass Group | D26: =left(E26, 3) -> CPG | E26: CPG.L | F26: {=xlookup(A26, sectors!B:B, sectors!C:C)} -> Hospitality | G26: {=XLOOKUP(A26, sectors!B:B, sectors!E:E)} -> Support Services | H26: Compass Group plc is a British multinational contract foodservice company. It is the largest contract foodservice company in Europe, ahead of Sodexo, employing over 500,000 people. | I26: 04083914 | J26: ="https://find-and-update.company-information.service.gov.uk/company/"&$I26 -> https://find-and-update.company-information.service.gov.uk/company/04083914 | K26: compass | L26: Compass Group | M26: https://www.glassdoor.co.uk/Overview/Working-at-Compass-Group-EI_IE10832.11,24.htm
A27: CRDA | B27: Croda International | C27: {=xlookup(B27, sectors!A:A, sectors!A:A)} -> Croda International | D27: CRDA | E27: CRDA.L | F27: {=xlookup(A27, sectors!B:B, sectors!C:C)} -> Engineering & Construction | G27: {=XLOOKUP(A27, sectors!B:B, sectors!E:E)} -> Chemicals | H27: Croda International plc is a British speciality chemicals company. | I27: 00206132 | J27: ="https://find-and-update.company-information.service.gov.uk/company/"&$I27 -> https://find-and-update.company-information.service.gov.uk/company/00206132 | K27: croda | M27: https://www.glassdoor.co.uk/Overview/Working-at-Croda-EI_IE10140.11,16.htm
A28: CRH | B28: CRH | C28: CRH plc | D28: =left(E28, 3) -> CRH | E28: CRH.L | F28: {=xlookup(A28, sectors!B:B, sectors!C:C)} -> Engineering & Construction | G28: {=XLOOKUP(A28, sectors!B:B, sectors!E:E)} -> Construction & Materials | H28: CRH plc is an international group of diversified building materials businesses. It manufactures and supplies a wide range of products for the construction industry. | I28: n/a | K28: crh | L28: CRH PLC | M28: https://www.glassdoor.co.uk/Overview/Working-at-CRH-EI_IE10480.11,14.htm
A29: CTEC | B29: Convatec | C29: Convatec Group | D29: CTEC | E29: CTEC.L | F29: {=xlookup(A29, sectors!B:B, sectors!C:C)} -> Healthcare & Pharmaceutical | G29: {=XLOOKUP(A29, sectors!B:B, sectors!E:E)} -> Health Care | H29: Convatec Group plc is a medical products and technologies company, offering products and services in the areas of wound and skin care, ostomy care, continence and critical care and infusion devices. | I29: 10361298 | J29: ="https://find-and-update.company-information.service.gov.uk/company/"&$I29 -> https://find-and-update.company-information.service.gov.uk/company/10361298 | K29: convatec | M29: https://www.glassdoor.co.uk/Overview/Working-at-ConvaTec-EI_IE13863.11,19.htm
A30: DCC | B30: DCC | C30: DCC plc | D30: =left(E30, 3) -> DCC | E30: DCC.L | F30: {=xlookup(A30, sectors!B:B, sectors!C:C)} -> Retail & Services | G30: {=XLOOKUP(A30, sectors!B:B, sectors!E:E)} -> Support Services | H30: DCC plc is a leading Irish international sales, marketing and support services group operating in 22 countries. The Group operates across three sectors: energy, healthcare and technology, employing over 16,000. | I30: n/a | K30: dcc | M30: https://www.glassdoor.co.uk/Overview/Working-at-DCC-EI_IE12649.11,14.htm
A31: DGE | B31: Diageo | C31: {=xlookup(B31, sectors!A:A, sectors!A:A)} -> Diageo | D31: =left(E31, 3) -> DGE | E31: DGE.L | F31: {=xlookup(A31, sectors!B:B, sectors!C:C)} -> Food & Beverage | G31: {=XLOOKUP(A31, sectors!B:B, sectors!E:E)} -> Beverages | H31: Diageo plc is a British multinational alcoholic beverage company. It operates from 132 sites around the world. It is a major distributor of Scotch whisky and other spirits. | I31: 00023307 | J31: ="https://find-and-update.company-information.service.gov.uk/company/"&$I31 -> https://find-and-update.company-information.service.gov.uk/company/00023307 | K31: diageo | L31: Diageo | M31: https://www.glassdoor.co.uk/Overview/Working-at-Diageo-EI_IE7438.11,17.htm
A32: EDV | B32: Endeavour Mining | C32: {=xlookup(B32, sectors!A:A, sectors!A:A)} -> Endeavour Mining | D32: =left(E32, 3) -> EDV | E32: EDV.L | F32: {=xlookup(A32, sectors!B:B, sectors!C:C)} -> Mining & Extraction | G32: {=XLOOKUP(A32, sectors!B:B, sectors!E:E)} -> Mining | H32: Endeavour Mining is a multinational mining company that owns and operates gold mines in Côte d'Ivoire, Burkina Faso and Senegal. | I32: 13280545 | J32: ="https://find-and-update.company-information.service.gov.uk/company/"&$I32 -> https://find-and-update.company-information.service.gov.uk/company/13280545 | K32: endeavour mining | M32: https://www.glassdoor.co.uk/Overview/Working-at-Endeavour-EI_IE1453795.11,20.htm
A33: EXPN | B33: Experian | C33: {=xlookup(B33, sectors!A:A, sectors!A:A)} -> Experian | D33: EXPN | E33: EXPN.L | F33: {=xlookup(A33, sectors!B:B, sectors!C:C)} -> Retail & Services | G33: {=XLOOKUP(A33, sectors!B:B, sectors!E:E)} -> Support Services | H33: Experian is a multinational data analytics and consumer credit reporting company headquartered in Dublin, Ireland. Experian collects and aggregates information on over 1 billion people and businesses including 235 million individual U.S. consumers and more than 25 million U.S. businesses. | I33: n/a | K33: experian | L33: Experian | M33: https://www.glassdoor.co.uk/Overview/Working-at-Experian-EI_IE42406.11,19.htm
A34: FCIT | B34: F&C Investment Trust | C34: Foreign & Colonial Investment Trust | D34: FCIT | E34: FCIT.L | F34: {=xlookup(A34, sectors!B:B, sectors!C:C)} -> Financial Services | G34: {=XLOOKUP(A34, sectors!B:B, sectors!E:E)} -> Financial Services | H34: Foreign & Colonial Investment Trust (F&C) is a publicly traded investment trust. | I34: 00012901 | J34: ="https://find-and-update.company-information.service.gov.uk/company/"&$I34 -> https://find-and-update.company-information.service.gov.uk/company/00012901 | K34: f&c | M34: https://www.glassdoor.co.uk/Overview/Working-at-F-and-C-Asset-Management-EI_IE13299.11,35.htm
A35: FLTR | B35: Flutter Entertainment | C35: {=xlookup(B35, sectors!A:A, sectors!A:A)} -> Flutter Entertainment | D35: FLTR | E35: FLTR.L | F35: {=xlookup(A35, sectors!B:B, sectors!C:C)} -> Retail & Services | G35: {=XLOOKUP(A35, sectors!B:B, sectors!E:E)} -> Travel & Leisure | H35: Flutter Entertainment plc, formerly Paddy Power Betfair plc, is an international sports betting and gambling company. It owns brands such as Betfair, FanDuel, Paddy Power, PokerStars, Sky Betting & Gaming, and Sportsbet. | I35: n/a | K35: flutter entertainment, paddy power, betfair | M35: https://www.glassdoor.co.uk/Overview/Working-at-Paddy-Power-Betfair-EI_IE100546.11,30.htm
A36: FRAS | B36: Frasers Group | C36: {=xlookup(B36, sectors!A:A, sectors!A:A)} -> Frasers Group | D36: FRAS | E36: FRAS.L | F36: {=xlookup(A36, sectors!B:B, sectors!C:C)} -> Real Estate | G36: {=XLOOKUP(A36, sectors!B:B, sectors!E:E)} -> Retail | H36: Frasers Group is a fashion company, and owns brands such as Sports Direct, House of Fraser, Frasers, FLANNELS, GAME, Jack Wills, Sofa.com, Evans Cycles, USC, and Everlast. | I36: 06035106 | J36: ="https://find-and-update.company-information.service.gov.uk/company/"&$I36 -> https://find-and-update.company-information.service.gov.uk/company/06035106 | K36: frasers, house of fraser, sports direct | L36: Frasers Group PLC | M36: https://www.glassdoor.co.uk/Overview/Working-at-Frasers-Group-EI_IE3870826.11,24.htm
A37: FRES | B37: Fresnillo | C37: Fresnillo plc | D37: FRES | E37: FRES.L | F37: {=xlookup(A37, sectors!B:B, sectors!C:C)} -> Mining & Extraction | G37: {=XLOOKUP(A37, sectors!B:B, sectors!E:E)} -> Mining | H37: Fresnillo plc is a Mexican precious metals mining company incorporated in the United Kingdom and headquartered in Mexico City. Fresnillo is the world's largest producer of silver from ore and Mexico's second-largest gold miner. | I37: 06344120 | J37: ="https://find-and-update.company-information.service.gov.uk/company/"&$I37 -> https://find-and-update.company-information.service.gov.uk/company/06344120 | K37: fresnillo | M37: https://www.glassdoor.co.uk/Overview/Working-at-Fresnillo-EI_IE157136.11,20.htm
A38: GLEN | B38: Glencore | C38: {=xlookup(B38, sectors!A:A, sectors!A:A)} -> Glencore | D38: GLEN | E38: GLEN.L | F38: {=xlookup(A38, sectors!B:B, sectors!C:C)} -> Mining & Extraction | G38: {=XLOOKUP(A38, sectors!B:B, sectors!E:E)} -> Mining | H38: Glencore plc is a Swiss multinational commodity trading and mining company with headquarters in Baar, Switzerland. Glencore's oil and gas head office is in London and its registered office is in Saint Helier, Jersey. The current company was created through a merger of Glencore with Xstrata on 2 May 2013. | I38: n/a | K38: glencore | L38: Glencore | M38: https://www.glassdoor.co.uk/Overview/Working-at-Glencore-EI_IE12231.11,19.htm
A39: GSK | B39: GSK | C39: GSK plc | D39: =left(E39, 3) -> GSK | E39: GSK.L | F39: {=xlookup(A39, sectors!B:B, sectors!C:C)} -> Healthcare & Pharmaceutical | G39: {=XLOOKUP(A39, sectors!B:B, sectors!E:E)} -> Pharmaceuticals & Biotechnology | H39: GSK plc, is a British multinational pharmaceutical and biotechnology company with global headquarters in London. | I39: 03888792 | J39: ="https://find-and-update.company-information.service.gov.uk/company/"&$I39 -> https://find-and-update.company-information.service.gov.uk/company/03888792 | K39: glaxosmithkline | L39: GlaxoSmithKline | M39: https://www.glassdoor.co.uk/Overview/Working-at-GlaxoSmithKline-EI_IE3477.11,26.htm
A40: GVC | B40: Entain | C40: {=xlookup(B40, sectors!A:A, sectors!A:A)} -> Entain | D40: =left(E40, 3) -> ENT | E40: ENT.L | F40: {=xlookup(A40, sectors!B:B, sectors!C:C)} -> Retail & Services | G40: {=XLOOKUP(A40, sectors!B:B, sectors!E:E)} -> Travel & Leisure | H40: Entain plc, formerly GVC Holdings, is an international sports betting and gambling company. It is listed on the London Stock Exchange and is a constituent of the FTSE 100 Index. It owns brands such as bwin, Coral, Ladbrokes, PartyPoker and Sportingbet. | I40: n/a | K40: ladbrokes | M40: https://www.glassdoor.co.uk/Overview/Working-at-GVC-Group-EI_IE341832.11,20.htm
A41: HL. | B41: Hargreaves Lansdown | C41: {=xlookup(B41, sectors!A:A, sectors!A:A)} -> Hargreaves Lansdown | D41: =left(E41, 3) -> HL. | E41: HL.L | F41: {=xlookup(A41, sectors!B:B, sectors!C:C)} -> Financial Services | G41: {=XLOOKUP(A41, sectors!B:B, sectors!E:E)} -> Financial Services | H41: Hargreaves Lansdown plc is a British financial service company based in Bristol, England. It sells funds and shares and related products to retail investors in the United Kingdom. The company is listed on the London Stock Exchange and is a constituent of the FTSE 100 Index. | I41: 02122142 | J41: ="https://find-and-update.company-information.service.gov.uk/company/"&$I41 -> https://find-and-update.company-information.service.gov.uk/company/02122142 | K41: hargreaves lansdown | M41: https://www.glassdoor.co.uk/Overview/Working-at-Hargreaves-Lansdown-EI_IE100339.11,30.htm
A42: HLMA | B42: Halma | C42: Halma plc | D42: HLMA | E42: HLMA.L | F42: {=xlookup(A42, sectors!B:B, sectors!C:C)} -> Retail & Services | G42: {=XLOOKUP(A42, sectors!B:B, sectors!E:E)} -> Electronic & Electrical Equipment | H42: Halma plc is a British global group of safety equipment companies that makes products for hazard detection and life protection based in Amersham, England. It is listed on the London Stock Exchange and is a constituent of the FTSE 100 Index. | I42: 00040932 | J42: ="https://find-and-update.company-information.service.gov.uk/company/"&$I42 -> https://find-and-update.company-information.service.gov.uk/company/00040932 | K42: halma | M42: https://www.glassdoor.co.uk/Overview/Working-at-Halma-EI_IE10162.11,16.htm
A43: HLN | B43: Haleon | C43: {=xlookup(B43, sectors!A:A, sectors!A:A)} -> Haleon | D43: =left(E43, 3) -> HLN | E43: HLN.L | F43: {=xlookup(A43, sectors!B:B, sectors!C:C)} -> Healthcare & Pharmaceutical | G43: {=XLOOKUP(A43, sectors!B:B, sectors!E:E)} -> Pharmaceuticals & Biotechnology | H43: Haleon plc is a British multinational consumer healthcare company with headquarters in Weybridge, England. It is one of the largest consumer healthcare business in the world, with brands including Sensodyne toothpaste, Panadol and Advil painkillers and Centrum vitamins. | I43: 13691224 | J43: ="https://find-and-update.company-information.service.gov.uk/company/"&$I43 -> https://find-and-update.company-information.service.gov.uk/company/13691224 | K43: haleon | M43: https://www.glassdoor.co.uk/Overview/Working-at-Haleon-EI_IE7672306.11,17.htm
A44: HSBA | B44: HSBC | C44: Hsbc Hldgs | D44: HSBA | E44: HSBA.L | F44: {=xlookup(A44, sectors!B:B, sectors!C:C)} -> Financial Services | G44: {=XLOOKUP(A44, sectors!B:B, sectors!E:E)} -> Banks | H44: HSBC is a British universal bank and financial services group headquartered in London, England, with unique historical and business links to East Asia and a highly multinational footprint. It is the largest Europe-based bank by total assets, ahead of BNP Paribas, with US$2.953 trillion as of December 2021. | I44: 00617987 | J44: ="https://find-and-update.company-information.service.gov.uk/company/"&$I44 -> https://find-and-update.company-information.service.gov.uk/company/00617987 | K44: hsbc | L44: HSBC | M44: https://www.glassdoor.co.uk/Overview/Working-at-HSBC-Holdings-EI_IE3482.11,24.htm
A45: HSX | B45: Hiscox | C45: Hiscox Ld | D45: =left(E45, 3) -> HSX | E45: HSX.L | F45: {=xlookup(A45, sectors!B:B, sectors!C:C)} -> Financial Services | G45: {=XLOOKUP(A45, sectors!B:B, sectors!E:E)} -> Insurance | H45: Hiscox Ltd. is an Anglo-Bermudan insurance provider, listed on the London Stock Exchange. An underwriter at Lloyd's of London, the company largely specialises in niche areas of the market, offering ... | I45: 02837811 | J45: ="https://find-and-update.company-information.service.gov.uk/company/"&$I45 -> https://find-and-update.company-information.service.gov.uk/company/02837811 | K45: hiscox | M45: https://www.glassdoor.co.uk/Overview/Working-at-Hiscox-EI_IE18106.11,17.htm
A46: IAG | B46: International Airlines Group | C46: Intl Consolidated Airlines Group Sa | D46: =left(E46, 3) -> IAG | E46: IAG.L | F46: {=xlookup(A46, sectors!B:B, sectors!C:C)} -> Hospitality | G46: {=XLOOKUP(A46, sectors!B:B, sectors!E:E)} -> Travel & Leisure | H46: International Consolidated Airlines Group S.A., trading as International Airlines Group and usually shortened to IAG, is an Anglo-Spanish multinational airline holding company with its registered office in Madrid, Spain, and its corporate headquarters in London, England. | I46: FC029884 | J46: ="https://find-and-update.company-information.service.gov.uk/company/"&$I46 -> https://find-and-update.company-information.service.gov.uk/company/FC029884 | K46: international airlines, british airways | L46: International Airlines Group | M46: https://www.glassdoor.co.uk/Overview/Working-at-International-Airlines-Group-EI_IE823718.11,39.htm
A47: IHG | B47: IHG Hotels & Resorts | C47: Intercontinental Hotels Group | D47: =left(E47, 3) -> IHG | E47: IHG.L | F47: {=xlookup(A47, sectors!B:B, sectors!C:C)} -> Hospitality | G47: {=XLOOKUP(A47, sectors!B:B, sectors!E:E)} -> Travel & Leisure | H47: InterContinental Hotels Group, marketed as IHG Hotels & Resorts, is a British multinational hospitality company headquartered in Windsor, England. It is listed on the London Stock Exchange and the New York Stock Exchange. It is also a constituent of the FTSE 100 Index. | I47: 05134420 | J47: ="https://find-and-update.company-information.service.gov.uk/company/"&$I47 -> https://find-and-update.company-information.service.gov.uk/company/05134420 | K47: intercontinental hotels | L47: InterContinental Hotels | M47: https://www.glassdoor.co.uk/Overview/Working-at-InterContinental-Hotels-Group-EI_IE4232.11,40.htm
A48: III | B48: 3i | C48: 3I Group | D48: =left(E48, 3) -> III | E48: III.L | F48: {=xlookup(A48, sectors!B:B, sectors!C:C)} -> Financial Services | G48: {=XLOOKUP(A48, sectors!B:B, sectors!E:E)} -> Financial Services | H48: 3i Group plc is a British multinational private equity and venture capital company based in London, England. 3i is listed on the London Stock Exchange and is a constituent of the FTSE 100 Index. | I48: 01142830 | J48: ="https://find-and-update.company-information.service.gov.uk/company/"&$I48 -> https://find-and-update.company-information.service.gov.uk/company/01142830 | K48: 3i | M48: https://www.glassdoor.co.uk/Overview/Working-at-3i-Group-EI_IE5365.11,19.htm
A49: IMB | B49: Imperial Brands | C49: {=xlookup(B49, sectors!A:A, sectors!A:A)} -> Imperial Brands | D49: =left(E49, 3) -> IMB | E49: IMB.L | F49: {=xlookup(A49, sectors!B:B, sectors!C:C)} -> Tobacco | G49: {=XLOOKUP(A49, sectors!B:B, sectors!E:E)} -> Tobacco | H49: Imperial Brands plc, is a British multinational tobacco company headquartered in London and Bristol, England. | I49: 03236483 | J49: ="https://find-and-update.company-information.service.gov.uk/company/"&$I49 -> https://find-and-update.company-information.service.gov.uk/company/03236483 | K49: imperial brands | L49: Imperial Brands | M49: https://www.glassdoor.co.uk/Overview/Working-at-Imperial-Brands-EI_IE6425.11,26.htm
A50: INFR | B50: Informa | C50: {=xlookup(B50, sectors!A:A, sectors!A:A)} -> Informa | D50: =left(E50, 3) -> INF | E50: INF.L | F50: {=xlookup(A50, sectors!B:B, sectors!C:C)} -> Retail & Services | G50: {=XLOOKUP(A50, sectors!B:B, sectors!E:E)} -> Media | H50: Informa plc is a British publishing, business intelligence, and exhibitions group based in London, England. It is listed on the London Stock Exchange and is a constituent of the FTSE 100 Index. It has offices in 43 countries and around 11,000 employees. | I50: 08860726 | J50: ="https://find-and-update.company-information.service.gov.uk/company/"&$I50 -> https://find-and-update.company-information.service.gov.uk/company/08860726 | K50: informa | M50: https://www.glassdoor.co.uk/Overview/Working-at-Informa-EI_IE9185.11,18.htm
A51: ITRK | B51: Intertek | C51: Intertek Group | D51: ITRK | E51: ITRK.L | F51: {=xlookup(A51, sectors!B:B, sectors!C:C)} -> Retail & Services | G51: {=XLOOKUP(A51, sectors!B:B, sectors!E:E)} -> Support Services | H51: Intertek Group plc is a British multinational assurance, inspection, product testing and certification company headquartered in London, England. It is listed on the London Stock Exchange and is a constituent of the FTSE 100 Index. | I51: 04267576 | J51: ="https://find-and-update.company-information.service.gov.uk/company/"&$I51 -> https://find-and-update.company-information.service.gov.uk/company/04267576 | K51: intertek | M51: https://www.glassdoor.co.uk/Overview/Working-at-Intertek-EI_IE15251.11,19.htm
A52: JD. | B52: JD Sports | C52: Jd Sports Fashion | D52: =left(E52, 3) -> JD. | E52: JD.L | F52: {=xlookup(A52, sectors!B:B, sectors!C:C)} -> Retail & Services | G52: {=XLOOKUP(A52, sectors!B:B, sectors!E:E)} -> General Retailers | H52: JD Sports Fashion plc, commonly known as JD Sports, JD or JD Group is a British sports-fashion retail company based in Bury, Greater Manchester, England. It is listed on the London Stock Exchange and is a constituent of the FTSE 100 Index. The Pentland Group owns 55% of the company. | I52: 01888425 | J52: ="https://find-and-update.company-information.service.gov.uk/company/"&$I52 -> https://find-and-update.company-information.service.gov.uk/company/01888425 | K52: jd sports | L52: JD Sports Fashion | M52: https://www.glassdoor.co.uk/Overview/Working-at-JD-Sports-Fashion-EI_IE13180.11,28.htm
A53: JMAT | B53: Johnson Matthey | C53: {=xlookup(B53, sectors!A:A, sectors!A:A)} -> Johnson Matthey | D53: JMAT | E53: JMAT.L | F53: {=xlookup(A53, sectors!B:B, sectors!C:C)} -> Engineering & Construction | G53: {=XLOOKUP(A53, sectors!B:B, sectors!E:E)} -> Chemicals | H53: Johnson Matthey is a British multinational speciality chemicals and sustainable technologies company headquartered in London, England. It is listed on the London Stock Exchange and is a constituent of the FTSE 100 Index. | I53: 00033774 | J53: ="https://find-and-update.company-information.service.gov.uk/company/"&$I53 -> https://find-and-update.company-information.service.gov.uk/company/00033774 | K53: johnson matthey | M53: https://www.glassdoor.co.uk/Overview/Working-at-Johnson-Matthey-EI_IE823708.11,26.htm
A54: KGF | B54: Kingfisher | C54: Kingfisher plc | D54: =left(E54, 3) -> KGF | E54: KGF.L | F54: {=xlookup(A54, sectors!B:B, sectors!C:C)} -> Retail & Services | G54: {=XLOOKUP(A54, sectors!B:B, sectors!E:E)} -> Retailers | H54: Kingfisher plc is a British multinational retailing company headquartered in London, England. It has over 1,300 stores in nine countries, and its brands include B&Q, Castorama, Brico Dépôt and Screwfix. Kingfisher is listed on the London Stock Exchange, and is a constituent of the FTSE 100 Index. | I54: 01664812 | J54: ="https://find-and-update.company-information.service.gov.uk/company/"&$I54 -> https://find-and-update.company-information.service.gov.uk/company/01664812 | K54: kingfisher | M54: https://www.glassdoor.co.uk/Overview/Working-at-Kingfisher-EI_IE10182.11,21.htm
A55: LAND | B55: Land Securities | C55: Land Securities Group | D55: LAND | E55: LAND.L | F55: {=xlookup(A55, sectors!B:B, sectors!C:C)} -> Real Estate | G55: {=XLOOKUP(A55, sectors!B:B, sectors!E:E)} -> Real Estate Investment Trusts | H55: Land Securities Group plc is the largest commercial property development and investment company in the United Kingdom. The firm became a real estate investment trust when REITs were introduced in the United Kingdom in January 2007. | I55: 04369054 | J55: ="https://find-and-update.company-information.service.gov.uk/company/"&$I55 -> https://find-and-update.company-information.service.gov.uk/company/04369054 | K55: land securities, landsec | M55: https://www.glassdoor.co.uk/Overview/Working-at-Landsec-EI_IE10187.11,18.htm
A56: LGEN | B56: Legal & General | C56: Legal & General Group | D56: LGEN | E56: LGEN.L | F56: {=xlookup(A56, sectors!B:B, sectors!C:C)} -> Financial Services | G56: {=XLOOKUP(A56, sectors!B:B, sectors!E:E)} -> Life Insurance | H56: Legal & General Group plc, commonly known as Legal & General, is a British multinational financial services and asset management company headquartered in London, England. Its products and services include investment management, lifetime mortgages, pensions, annuities, and life assurance. | I56: 01417162 | J56: ="https://find-and-update.company-information.service.gov.uk/company/"&$I56 -> https://find-and-update.company-information.service.gov.uk/company/01417162 | K56: legal general | M56: https://www.glassdoor.co.uk/Overview/Working-at-Legal-and-General-EI_IE10189.11,28.htm
A57: LLOY | B57: Lloyds Banking Group | C57: {=xlookup(B57, sectors!A:A, sectors!A:A)} -> Lloyds Banking Group | D57: LLOY | E57: LLOY.L | F57: {=xlookup(A57, sectors!B:B, sectors!C:C)} -> Financial Services | G57: {=XLOOKUP(A57, sectors!B:B, sectors!E:E)} -> Banks | H57: Lloyds Banking Group is a British financial institution formed through the acquisition of HBOS by Lloyds TSB in 2009. It is one of the UK's largest financial services organisations, with 30 million customers and 65,000 employees. | I57: SC095000 | J57: ="https://find-and-update.company-information.service.gov.uk/company/"&$I57 -> https://find-and-update.company-information.service.gov.uk/company/SC095000 | K57: lloyds | L57: Lloyds Banking Group | M57: https://www.glassdoor.co.uk/Overview/Working-at-Lloyds-Banking-Group-EI_IE316191.11,31.htm
A58: LSE | B58: London Stock Exchange Group | C58: {=xlookup(B58, sectors!A:A, sectors!A:A)} -> London Stock Exchange Group | D58: LSE | E58: LSEG.L | F58: {=xlookup(A58, sectors!B:B, sectors!C:C)} -> Financial Services | G58: {=XLOOKUP(A58, sectors!B:B, sectors!E:E)} -> Financial Services | H58: London Stock Exchange Group plc (LSEG) is a United Kingdom-based stock exchange and financial information company headquartered in the City of London, England. It owns the London Stock Exchange (on which it is also listed), Refinitiv, LSEG Technology,[2] FTSE Russell, and majority stakes in LCH and Tradeweb. | I58: 05369106 | J58: ="https://find-and-update.company-information.service.gov.uk/company/"&$I58 -> https://find-and-update.company-information.service.gov.uk/company/05369106 | K58: london stock exchange | M58: https://www.glassdoor.co.uk/Overview/Working-at-London-Stock-Exchange-Group-EI_IE11860.11,38.htm
A59: MNDI | B59: Mondi | C59: {=xlookup(B59, sectors!A:A, sectors!A:A)} -> Mondi | D59: MNDI | E59: MNDI.L | F59: {=xlookup(A59, sectors!B:B, sectors!C:C)} -> Retail & Services | G59: {=XLOOKUP(A59, sectors!B:B, sectors!E:E)} -> Forestry & Paper | H59: Mondi plc is a multinational packaging and paper group employing around 21,000 people with around 100 production sites across more than 30 countries, predominantly in Europe, Russia, North America and South Africa. Group offices are located in Weybridge, United Kingdom and Vienna, Austria. | I59: 06209386 | J59: ="https://find-and-update.company-information.service.gov.uk/company/"&$I59 -> https://find-and-update.company-information.service.gov.uk/company/06209386 | K59: mondi | M59: https://www.glassdoor.co.uk/Overview/Working-at-Mondi-Group-EI_IE42692.11,22.htm
A60: MNG | B60: M&G | C60: {=xlookup(B60, sectors!A:A, sectors!A:A)} -> M&G | D60: =left(E60, 3) -> MNG | E60: MNG.L | F60: {=xlookup(A60, sectors!B:B, sectors!C:C)} -> Financial Services | G60: {=XLOOKUP(A60, sectors!B:B, sectors!E:E)} -> Asset Managers | H60: M&G plc is a global investment manager headquartered in the City of London. Since its de-merger from Prudential plc, it has been listed on the London Stock Exchange and is a constituent of the FTSE 100 Index. | I60: 11444019 | J60: ="https://find-and-update.company-information.service.gov.uk/company/"&$I60 -> https://find-and-update.company-information.service.gov.uk/company/11444019 | K60: m&g | M60: https://www.glassdoor.co.uk/Overview/Working-at-M-and-G-plc-EI_IE36436.11,22.htm
A61: MRO | B61: Melrose Industries | C61: {=xlookup(B61, sectors!A:A, sectors!A:A)} -> Melrose Industries | D61: =left(E61, 3) -> MRO | E61: MRO.L | F61: {=xlookup(A61, sectors!B:B, sectors!C:C)} -> Engineering & Construction | G61: {=XLOOKUP(A61, sectors!B:B, sectors!E:E)} -> Automobiles & Parts | H61: Melrose Industries plc is a British manufacturing company based in London. It specialises in buying, investing in, and divesting engineering companies. Its shares are listed on the London Stock Exchange as a constituent of the FTSE 100 Index. Melrose serves customers in the United Kingdom and United States. | I61: 09800044 | J61: ="https://find-and-update.company-information.service.gov.uk/company/"&$I61 -> https://find-and-update.company-information.service.gov.uk/company/09800044 | K61: melrose industries | L61: Melrose Industries | M61: https://www.glassdoor.co.uk/Reviews/Melrose-Industries-Reviews-E229812.htm
A62: NG. | B62: National Grid | C62: National Grid plc | D62: =left(E62, 3) -> NG. | E62: NG.L | F62: {=xlookup(A62, sectors!B:B, sectors!C:C)} -> Utilities | G62: {=XLOOKUP(A62, sectors!B:B, sectors!E:E)} -> Gas, Water & Multi-utilities | H62: National Grid plc is a British multinational electricity and gas utility company headquartered in London, England. | I62: 04031152 | J62: ="https://find-and-update.company-information.service.gov.uk/company/"&$I62 -> https://find-and-update.company-information.service.gov.uk/company/04031152 | K62: national grid | L62: National Grid | M62: https://www.glassdoor.co.uk/Overview/Working-at-National-Grid-EI_IE474.11,24.htm
A63: NXT | B63: Next | C63: Next plc | D63: =left(E63, 3) -> NXT | E63: NXT.L | F63: {=xlookup(A63, sectors!B:B, sectors!C:C)} -> Retail & Services | G63: {=XLOOKUP(A63, sectors!B:B, sectors!E:E)} -> General Retailers | H63: Next plc is a British multinational clothing, footwear and home products retailer, which has its headquarters in Enderby, England. It has around 700 stores, of which circa 500 are in the United Kingdom, and circa 200 across Europe, Asia and the Middle East. | I63: 04412362 | J63: ="https://find-and-update.company-information.service.gov.uk/company/"&$I63 -> https://find-and-update.company-information.service.gov.uk/company/04412362 | K63: next | M63: https://www.glassdoor.co.uk/Overview/Working-at-next-EI_IE7749.11,15.htm
A64: OCDO | B64: Ocado Group | C64: {=xlookup(B64, sectors!A:A, sectors!A:A)} -> Ocado Group | D64: OCDO | E64: OCDO.L | F64: {=xlookup(A64, sectors!B:B, sectors!C:C)} -> Food & Beverage | G64: {=XLOOKUP(A64, sectors!B:B, sectors!E:E)} -> Food & Drug Retailers | H64: Ocado Group is a British business based in Hatfield, England, which licenses grocery technology. It also owns a 50% share in the UK retail business, Ocado.com. The company is listed on the London Stock Exchange and is a constituent of the FTSE 100 Index. | I64: 07098618 | J64: ="https://find-and-update.company-information.service.gov.uk/company/"&$I64 -> https://find-and-update.company-information.service.gov.uk/company/07098618 | K64: ocado | M64: https://www.glassdoor.co.uk/Overview/Working-at-Ocado-Group-EI_IE22337.11,22.htm
A65: PHNX | B65: Phoenix Group | C65: Phoenix Group Holdings | D65: PHNX | E65: PHNX.L | F65: {=xlookup(A65, sectors!B:B, sectors!C:C)} -> Financial Services | G65: {=XLOOKUP(A65, sectors!B:B, sectors!E:E)} -> Life Insurance | H65: Phoenix Group Holdings plc is a provider of insurance services based in London, England. It is listed on the London Stock Exchange and is a constituent of the FTSE 100 Index. | I65: 11606773 | J65: ="https://find-and-update.company-information.service.gov.uk/company/"&$I65 -> https://find-and-update.company-information.service.gov.uk/company/11606773 | K65: phoenix | M65: https://www.glassdoor.co.uk/Overview/Working-at-Phoenix-Group-EI_IE35846.11,24.htm
A66: PRU | B66: Prudential | C66: Prudential plc | D66: =left(E66, 3) -> PRU | E66: PRU.L | F66: {=xlookup(A66, sectors!B:B, sectors!C:C)} -> Financial Services | G66: {=XLOOKUP(A66, sectors!B:B, sectors!E:E)} -> Life Insurance | H66: Prudential plc is a British multinational insurance company headquartered in London, England. It was founded in London in May 1848 to provide loans to professional and working people. | I66: 01397169 | J66: ="https://find-and-update.company-information.service.gov.uk/company/"&$I66 -> https://find-and-update.company-information.service.gov.uk/company/01397169 | K66: prudential | L66: Prudential (UK) | M66: https://www.glassdoor.co.uk/Overview/Working-at-Prudential-plc-EI_IE10215.11,25.htm
A67: PSH | B67: Pershing Square Holdings | C67: Pershing Square Holdings Ltd | D67: =left(E67, 3) -> PSH | E67: PSH.L | F67: {=xlookup(A67, sectors!B:B, sectors!C:C)} -> Financial Services | G67: {=XLOOKUP(A67, sectors!B:B, sectors!E:E)} -> Financial Services | H67: Pershing Square Holdings is a large British investment trust dedicated to long-term investments in North American companies. Established in 2012, the company is a constituent of the FTSE 100 Index. The chairman is Anne Farlow. The fund is managed by Bill Ackman of Pershing Square Capital Management. | I67: n/a | K67: pershing square
A68: PSN | B68: Persimmon | C68: Persimmon plc | D68: =left(E68, 3) -> PSN | E68: PSN.L | F68: {=xlookup(A68, sectors!B:B, sectors!C:C)} -> Engineering & Construction | G68: {=XLOOKUP(A68, sectors!B:B, sectors!E:E)} -> Household Goods & Home Construction | H68: Persimmon plc is a British housebuilding company, headquartered in York, England. The company is named after a horse which won the 1896 Derby and St. Leger for the Prince of Wales. It is listed on the London Stock Exchange and is a constituent of the FTSE 100 Index. | I68: 01818486 | J68: ="https://find-and-update.company-information.service.gov.uk/company/"&$I68 -> https://find-and-update.company-information.service.gov.uk/company/01818486 | K68: persimmon | M68: https://www.glassdoor.co.uk/Overview/Working-at-Persimmon-EI_IE10285.11,20.htm
A69: PSON | B69: Pearson | C69: Pearson plc | D69: PSON | E69: PSON.L | F69: {=xlookup(A69, sectors!B:B, sectors!C:C)} -> Retail & Services | G69: {=XLOOKUP(A69, sectors!B:B, sectors!E:E)} -> Media | H69: Pearson plc is a British multinational publishing and education company headquartered in London, England. It was founded as a construction business in the 1840s but switched to publishing in the 1920s. As of 2017, it is the largest education company, and it was once the largest book publisher in the world. | I69: 00053723 | J69: ="https://find-and-update.company-information.service.gov.uk/company/"&$I69 -> https://find-and-update.company-information.service.gov.uk/company/00053723 | K69: pearson | L69: Pearson | M69: https://www.glassdoor.co.uk/Overview/Working-at-Pearson-EI_IE3322.11,18.htm
A70: RB. | B70: Reckitt | C70: Reckitt Benckiser Group | D70: =left(E70, 3) -> RKT | E70: RKT.L | F70: Healthcare & Pharmaceutical | G70: Consumer Goods | H70: Reckitt Benckiser Group plc, trading as Reckitt, is a British multinational consumer goods company headquartered in Slough, England. It is a producer of health, hygiene and nutrition products. | I70: 06270876 | J70: ="https://find-and-update.company-information.service.gov.uk/company/"&$I70 -> https://find-and-update.company-information.service.gov.uk/company/06270876 | K70: reckitt benckiser | L70: Reckitt Benckiser | M70: https://www.glassdoor.co.uk/Overview/Working-at-RB-EI_IE3600.11,13.htm
A71: RBS | B71: Natwest Group | C71: {=xlookup(B71, sectors!A:A, sectors!A:A)} -> NatWest Group | D71: =left(E71, 3) -> NWG | E71: NWG.L | F71: {=xlookup(A71, sectors!B:B, sectors!C:C)} -> Financial Services | G71: {=XLOOKUP(A71, sectors!B:B, sectors!E:E)} -> Banks | H71: NatWest Group plc is a British banking and insurance holding company, based in Edinburgh, Scotland. The group operates a wide variety of banking brands offering personal and business banking, private banking, investment banking, insurance and corporate finance. | I71: SC045551 | J71: ="https://find-and-update.company-information.service.gov.uk/company/"&$I71 -> https://find-and-update.company-information.service.gov.uk/company/SC045551 | K71: natwest, rbs, royal bank of scotland | L71: Royal Bank of Scotland | M71: https://www.glassdoor.co.uk/Overview/Working-at-Royal-Bank-of-Scotland-EI_IE10222.11,33.htm
A72: RDSA | B72: Shell | C72: Shell plc | D72: SHEL | E72: SHEL.L | F72: Mining & Extraction | G72: Energy | H72: Shell plc is a British multinational oil and gas company headquartered in London, England. Shell is a public limited company with a primary listing on the London Stock Exchange and secondary listings on Euronext Amsterdam and the New York Stock Exchange. | I72: 04366849 | J72: ="https://find-and-update.company-information.service.gov.uk/company/"&$I72 -> https://find-and-update.company-information.service.gov.uk/company/04366849 | K72: shell, royal dutch shell | L72: Royal Dutch Shell | M72: https://www.glassdoor.co.uk/Overview/Working-at-Shell-EI_IE5833.11,16.htm
A73: REL | B73: Relx | C73: {=xlookup(B73, sectors!A:A, sectors!A:A)} -> RELX | D73: =left(E73, 3) -> REL | E73: REL.L | F73: {=xlookup(A73, sectors!B:B, sectors!C:C)} -> Retail & Services | G73: {=XLOOKUP(A73, sectors!B:B, sectors!E:E)} -> Media | H73: RELX plc is a British multinational information and analytics company headquartered in London, England. Its businesses provide scientific, technical and medical information and analytics; legal information and analytics; decision-making tools; and organise exhibitions. | I73: 00077536 | J73: ="https://find-and-update.company-information.service.gov.uk/company/"&$I73 -> https://find-and-update.company-information.service.gov.uk/company/00077536 | K73: relx | L73: RELX Group | M73: https://www.glassdoor.co.uk/Overview/Working-at-RELX-EI_IE1023378.11,15.htm
A74: RIO | B74: Rio Tinto | C74: {=xlookup(B74, sectors!A:A, sectors!A:A)} -> Rio Tinto | D74: =left(E74, 3) -> RIO | E74: RIO.L | F74: {=xlookup(A74, sectors!B:B, sectors!C:C)} -> Mining & Extraction | G74: {=XLOOKUP(A74, sectors!B:B, sectors!E:E)} -> Mining | H74: The Rio Tinto Company Limited was one of the founding companies of the Rio Tinto Group conglomerate, which was responsible of the exploitation of the Riotinto-Nerva mining basin in Minas de Riotinto between 1873 and 1954. | I74: 00719885 | J74: ="https://find-and-update.company-information.service.gov.uk/company/"&$I74 -> https://find-and-update.company-information.service.gov.uk/company/00719885 | K74: rio tinto | L74: Rio Tinto | M74: https://www.glassdoor.co.uk/Overview/Working-at-Rio-Tinto-EI_IE6685.11,20.htm
A75: RMV | B75: Rightmove | C75: {=xlookup(B75, sectors!A:A, sectors!A:A)} -> Rightmove | D75: =left(E75, 3) -> RMV | E75: RMV.L | F75: {=xlookup(A75, sectors!B:B, sectors!C:C)} -> Retail & Services | G75: {=XLOOKUP(A75, sectors!B:B, sectors!E:E)} -> Media | H75: Rightmove plc is a UK-based company which runs rightmove.co.uk, the UK's largest online real estate property portal. Rightmove is listed on the London Stock Exchange and is a constituent of the FTSE 100 Index. | I75: 06426485 | J75: ="https://find-and-update.company-information.service.gov.uk/company/"&$I75 -> https://find-and-update.company-information.service.gov.uk/company/06426485 | K75: rightmove | M75: https://www.glassdoor.co.uk/Overview/Working-at-Rightmove-EI_IE39764.11,20.htm
A76: RR. | B76: Rolls-Royce Holdings | C76: {=xlookup(B76, sectors!A:A, sectors!A:A)} -> Rolls-Royce Holdings | D76: =left(E76, 3) -> RR. | E76: RR.L | F76: {=xlookup(A76, sectors!B:B, sectors!C:C)} -> Engineering & Construction | G76: {=XLOOKUP(A76, sectors!B:B, sectors!E:E)} -> Aerospace & Defence | H76: Rolls-Royce Holdings plc is a British multinational aerospace and defence company incorporated in February 2011. The company owns Rolls-Royce, a business established in 1904 which today designs, manufactures and distributes power systems for aviation and other industries. | I76: 07524813 | J76: ="https://find-and-update.company-information.service.gov.uk/company/"&$I76 -> https://find-and-update.company-information.service.gov.uk/company/07524813 | K76: rolls-royce, rolls royce | L76: Rolls-Royce | M76: https://www.glassdoor.co.uk/Overview/Working-at-Rolls-Royce-EI_IE3505.11,22.htm
A77: RS1 | B77: RS Group | C77: RS Group plc | D77: =left(E77, 3) -> RS1 | E77: RS1.L | F77: {=xlookup(A77, sectors!B:B, sectors!C:C)} -> Engineering & Construction | G77: {=XLOOKUP(A77, sectors!B:B, sectors!E:E)} -> Industrials | H77: RS Group plc is a distributor of industrial and electronics products based in London, England. It is listed on the London Stock Exchange and is a constituent of the FTSE 100 Index. | I77: 00647788 | J77: ="https://find-and-update.company-information.service.gov.uk/company/"&$I77 -> https://find-and-update.company-information.service.gov.uk/company/00647788 | K77: rs group, electrocomponents | M77: https://www.glassdoor.co.uk/Overview/Working-at-RS-Group-EI_IE467935.11,19.htm
A78: RTO | B78: Rentokil Initial | C78: {=xlookup(B78, sectors!A:A, sectors!A:A)} -> Rentokil Initial | D78: =left(E78, 3) -> RTO | E78: RTO.L | F78: {=xlookup(A78, sectors!B:B, sectors!C:C)} -> Retail & Services | G78: {=XLOOKUP(A78, sectors!B:B, sectors!E:E)} -> Support Services | H78: Rentokil Initial is a British business services group based in Crawley, England. It was founded in 1925 as a pest-control business but subsequently expanded and diversified, in part through organic ... | I78: 05393279 | J78: ="https://find-and-update.company-information.service.gov.uk/company/"&$I78 -> https://find-and-update.company-information.service.gov.uk/company/05393279 | K78: rentokil | M78: https://www.glassdoor.co.uk/Overview/Working-at-Rentokil-Initial-EI_IE10220.11,27.htm
A79: SBRY | B79: Sainsbury's | C79: Sainsbury's (J) | D79: SBRY | E79: SBRY.L | F79: {=xlookup(A79, sectors!B:B, sectors!C:C)} -> Food & Beverage | G79: {=XLOOKUP(A79, sectors!B:B, sectors!E:E)} -> Food & Drug Retailers | H79: J Sainsbury plc, trading as Sainsbury's, is the second largest chain of supermarkets in the United Kingdom, with a 14.6% share of UK supermarket sales in September 2022. | I79: 00185647 | J79: ="https://find-and-update.company-information.service.gov.uk/company/"&$I79 -> https://find-and-update.company-information.service.gov.uk/company/00185647 | K79: sainsbury | M79: https://www.glassdoor.co.uk/Overview/Working-at-J-Sainsbury-EI_IE2978.11,22.htm
A80: SDR | B80: Schroders | C80: {=xlookup(B80, sectors!A:A, sectors!A:A)} -> Schroders | D80: =left(E80, 3) -> SDR | E80: SDR.L | F80: {=xlookup(A80, sectors!B:B, sectors!C:C)} -> Financial Services | G80: {=XLOOKUP(A80, sectors!B:B, sectors!E:E)} -> Financial Services | H80: Schroders plc is a British multinational asset management company, founded in 1804 based in London, England. The company employs over 5,000 people worldwide in 32 locations around Europe, America, Asia, Africa and the Middle East. It is traded on the London Stock Exchange and is a constituent of the FTSE 100 Index. | I80: 03909886 | J80: ="https://find-and-update.company-information.service.gov.uk/company/"&$I80 -> https://find-and-update.company-information.service.gov.uk/company/03909886 | K80: schroder | M80: https://www.glassdoor.co.uk/Overview/Working-at-Schroders-EI_IE10512.11,20.htm
A81: SGE | B81: Sage Group | C81: {=xlookup(B81, sectors!A:A, sectors!A:A)} -> Sage Group | D81: =left(E81, 3) -> SGE | E81: SGE.L | F81: {=xlookup(A81, sectors!B:B, sectors!C:C)} -> Retail & Services | G81: {=XLOOKUP(A81, sectors!B:B, sectors!E:E)} -> Software & Computer Services | H81: The Sage Group plc, commonly known as Sage, is a British multinational enterprise software company based in Newcastle upon Tyne, England. | I81: 02231246 | J81: ="https://find-and-update.company-information.service.gov.uk/company/"&$I81 -> https://find-and-update.company-information.service.gov.uk/company/02231246 | K81: sage | M81: https://www.glassdoor.co.uk/Overview/Working-at-Sage-EI_IE1150.11,15.htm
A82: SGRO | B82: Segro | C82: {=xlookup(B82, sectors!A:A, sectors!A:A)} -> Segro | D82: SGRO | E82: SGRO.L | F82: {=xlookup(A82, sectors!B:B, sectors!C:C)} -> Real Estate | G82: {=XLOOKUP(A82, sectors!B:B, sectors!E:E)} -> Real Estate Investment Trusts | H82: SEGRO plc is a British property investment and development company. It develops and invests in property located in the UK and Continental Europe focusing on edge of town flexible business space. The firm switched to Real Estate Investment Trust status when REITs were introduced in the United Kingdom in January 2007. | I82: 00167591 | J82: ="https://find-and-update.company-information.service.gov.uk/company/"&$I82 -> https://find-and-update.company-information.service.gov.uk/company/00167591 | K82: segro | M82: https://www.glassdoor.co.uk/Overview/Working-at-SEGRO-EI_IE10232.11,16.htm
A83: SKG | B83: Smurfit Kappa | C83: Smurfit Kappa Group | D83: =left(E83, 3) -> SKG | E83: SKG.L | F83: {=xlookup(A83, sectors!B:B, sectors!C:C)} -> Retail & Services | G83: {=XLOOKUP(A83, sectors!B:B, sectors!E:E)} -> General Industrials | H83: The Smurfit Kappa Group plc is Europe's leading corrugated packaging company and one of the leading paper-based packaging companies in the world. It is listed on the London Stock Exchange and is a constituent of the FTSE 100 Index. | I83: n/a | K83: smurfit | L83: Smurfit Kappa | M83: https://www.glassdoor.co.uk/Overview/Working-at-Smurfit-Kappa-EI_IE10486.11,24.htm
A84: SMDS | B84: DS Smith | C84: Smith (Ds) | D84: SMDS | E84: SMDS.L | F84: {=xlookup(A84, sectors!B:B, sectors!C:C)} -> Retail & Services | G84: {=XLOOKUP(A84, sectors!B:B, sectors!E:E)} -> General Industrials | H84: DS Smith plc is a British multinational packaging business, headquartered in London, England. It is listed on the London Stock Exchange and is a constituent of the FTSE 100 Index. | I84: 01377658 | J84: ="https://find-and-update.company-information.service.gov.uk/company/"&$I84 -> https://find-and-update.company-information.service.gov.uk/company/01377658 | K84: ds smith | M84: https://www.glassdoor.co.uk/Overview/Working-at-DS-Smith-EI_IE10142.11,19.htm
A85: SMIN | B85: Smiths Group | C85: {=xlookup(B85, sectors!A:A, sectors!A:A)} -> Smiths Group | D85: SMIN | E85: SMIN.L | F85: {=xlookup(A85, sectors!B:B, sectors!C:C)} -> Engineering & Construction | G85: {=XLOOKUP(A85, sectors!B:B, sectors!E:E)} -> General Industrials | H85: Smiths Group plc is a British, multinational, diversified engineering business headquartered in London, England. It operates in over 50 countries and employs 14,600 staff. Smiths Group has its origins in a jewellery shop, S Smith & Sons, which was founded by the watchmaker and businessman Samuel Smith. | I85: 00137013 | J85: ="https://find-and-update.company-information.service.gov.uk/company/"&$I85 -> https://find-and-update.company-information.service.gov.uk/company/00137013 | K85: smiths group | L85: Smiths Group | M85: https://www.glassdoor.co.uk/Overview/Working-at-Smiths-Group-EI_IE10234.11,23.htm
A86: SMT | B86: Scottish Mortgage Investment Trust | C86: Scottish Mortgage Inv Tst | D86: =left(E86, 3) -> SMT | E86: SMT.L | F86: {=xlookup(A86, sectors!B:B, sectors!C:C)} -> Financial Services | G86: {=XLOOKUP(A86, sectors!B:B, sectors!E:E)} -> Equity Investment Instruments | H86: Scottish Mortgage Investment Trust is a publicly traded investment trust. It invests globally, looking for strong businesses with above-average returns. Scottish Mortgage is managed by Baillie Gifford & Co Limited, the Edinburgh-based investment management partnership. | I86: SC007058 | J86: ="https://find-and-update.company-information.service.gov.uk/company/"&$I86 -> https://find-and-update.company-information.service.gov.uk/company/SC007058 | K86: scottish mortgage | M86: https://www.glassdoor.co.uk/Overview/Working-at-Baillie-Gifford-EI_IE36741.11,26.htm
A87: SN. | B87: Smith & Nephew | C87: {=xlookup(B87, sectors!A:A, sectors!A:A)} -> Smith & Nephew | D87: =left(E87, 3) -> SN. | E87: SN.L | F87: {=xlookup(A87, sectors!B:B, sectors!C:C)} -> Engineering & Construction | G87: {=XLOOKUP(A87, sectors!B:B, sectors!E:E)} -> Health Care Equipment & Services | H87: Smith & Nephew plc, also known as Smith+Nephew, is a British multinational medical equipment manufacturing company headquartered in Watford, England. | I87: 00324357 | J87: ="https://find-and-update.company-information.service.gov.uk/company/"&$I87 -> https://find-and-update.company-information.service.gov.uk/company/00324357 | K87: smith & nephew, smith and nephew | L87: Smith & Nephew | M87: https://www.glassdoor.co.uk/Overview/Working-at-Smith-and-Nephew-EI_IE10233.11,27.htm
A88: SPX | B88: Spirax-Sarco Engineering | C88: {=xlookup(B88, sectors!A:A, sectors!A:A)} -> Spirax-Sarco Engineering | D88: =left(E88, 3) -> SPX | E88: SPX.L | F88: {=xlookup(A88, sectors!B:B, sectors!C:C)} -> Engineering & Construction | G88: {=XLOOKUP(A88, sectors!B:B, sectors!E:E)} -> Industrial Engineering | H88: Spirax-Sarco Engineering plc is a British manufacturer of steam management systems and peristaltic pumps and associated fluid path technologies. It is headquartered in Cheltenham, England. It is listed on the London Stock Exchange and is a constituent of the FTSE 100 Index. | I88: 00596337 | J88: ="https://find-and-update.company-information.service.gov.uk/company/"&$I88 -> https://find-and-update.company-information.service.gov.uk/company/00596337 | K88: spirax | M88: https://www.glassdoor.co.uk/Overview/Working-at-Spirax-Sarco-EI_IE292187.11,23.htm
A89: SSE | B89: SSE | C89: SSE plc | D89: =left(E89, 3) -> SSE | E89: SSE.L | F89: {=xlookup(A89, sectors!B:B, sectors!C:C)} -> Utilities | G89: {=XLOOKUP(A89, sectors!B:B, sectors!E:E)} -> Electricity | H89: SSE plc is a multinational energy company headquartered in Perth, Scotland. It is listed on the London Stock Exchange, and is a constituent of the FTSE 100 Index. SSE operates in the United Kingdom and Ireland. | I89: SC117119 | J89: ="https://find-and-update.company-information.service.gov.uk/company/"&$I89 -> https://find-and-update.company-information.service.gov.uk/company/SC117119 | K89: sse | M89: https://www.glassdoor.co.uk/Overview/Working-at-SSE-EI_IE8994.11,14.htm
A90: STAN | B90: Standard Chartered | C90: {=xlookup(B90, sectors!A:A, sectors!A:A)} -> Standard Chartered | D90: STAN | E90: STAN.L | F90: {=xlookup(A90, sectors!B:B, sectors!C:C)} -> Financial Services | G90: {=XLOOKUP(A90, sectors!B:B, sectors!E:E)} -> Banks | H90: Standard Chartered plc is a British multinational bank with operations in consumer, corporate and institutional banking, and treasury services. Despite being headquartered in the United Kingdom, it does not conduct retail banking in the UK, and around 90% of its profits come from Asia, Africa, and the Middle East. | I90: 00966425 | J90: ="https://find-and-update.company-information.service.gov.uk/company/"&$I90 -> https://find-and-update.company-information.service.gov.uk/company/00966425 | K90: standard chartered | L90: Standard Chartered | M90: https://www.glassdoor.co.uk/Overview/Working-at-Standard-Chartered-Bank-EI_IE226853.11,34.htm
A91: STJ | B91: St. James's Place | C91: St. James's Place plc | D91: =left(E91, 3) -> STJ | E91: STJ.L | F91: {=xlookup(A91, sectors!B:B, sectors!C:C)} -> Financial Services | G91: {=XLOOKUP(A91, sectors!B:B, sectors!E:E)} -> Financial Services | H91: St. James's Place plc, formerly St. James's Place Capital plc, is a British investment management company. The head office is in Cirencester, in Gloucestershire, and there are over twenty other offices in the United Kingdom. It is a combined adviser, fund manager and life insurance business. | I91: 03183415 | J91: ="https://find-and-update.company-information.service.gov.uk/company/"&$I91 -> https://find-and-update.company-information.service.gov.uk/company/03183415 | K91: st james's place | M91: https://www.glassdoor.co.uk/Overview/Working-at-St-James-s-Place-Wealth-Management-EI_IE10244.11,45.htm
A92: SVT | B92: Severn Trent | C92: {=xlookup(B92, sectors!A:A, sectors!A:A)} -> Severn Trent | D92: =left(E92, 3) -> SVT | E92: SVT.L | F92: {=xlookup(A92, sectors!B:B, sectors!C:C)} -> Utilities | G92: {=XLOOKUP(A92, sectors!B:B, sectors!E:E)} -> Gas, Water & Multi-utilities | H92: Severn Trent plc is a water company based in Coventry, England. It supplies 4.6 million households and business across the Midlands and Wales. It is traded on the London Stock Exchange and a constituent of the FTSE 100 Index. | I92: 02366619 | J92: ="https://find-and-update.company-information.service.gov.uk/company/"&$I92 -> https://find-and-update.company-information.service.gov.uk/company/02366619 | K92: severn trent | M92: https://www.glassdoor.co.uk/Overview/Working-at-Severn-Trent-EI_IE324366.11,23.htm
A93: TSCO | B93: Tesco | C93: {=xlookup(B93, sectors!A:A, sectors!A:A)} -> Tesco | D93: TSCO | E93: TSCO.L | F93: {=xlookup(A93, sectors!B:B, sectors!C:C)} -> Food & Beverage | G93: {=XLOOKUP(A93, sectors!B:B, sectors!E:E)} -> Food & Drug Retailers | H93: Tesco plc is a British multinational groceries and general merchandise retailer headquartered in Welwyn Garden City, England. In 2011 it was the third-largest retailer in the world measured by gross revenues and the ninth-largest in the world measured by revenues. | I93: 00445790 | J93: ="https://find-and-update.company-information.service.gov.uk/company/"&$I93 -> https://find-and-update.company-information.service.gov.uk/company/00445790 | K93: tesco | M93: https://www.glassdoor.co.uk/Overview/Working-at-Tesco-EI_IE10250.11,16.htm
A94: TW. | B94: Taylor Wimpey | C94: {=xlookup(B94, sectors!A:A, sectors!A:A)} -> Taylor Wimpey | D94: =left(E94, 3) -> TW. | E94: TW.L | F94: {=xlookup(A94, sectors!B:B, sectors!C:C)} -> Engineering & Construction | G94: {=XLOOKUP(A94, sectors!B:B, sectors!E:E)} -> Household Goods & Home Construction | H94: Taylor Wimpey plc is one of the largest home construction companies in the United Kingdom. The company was created from the merger of rivals Taylor Woodrow and George Wimpey on 3 July 2007. It is listed on the London Stock Exchange and is a constituent of the FTSE 100 Index. | I94: 00296805 | J94: ="https://find-and-update.company-information.service.gov.uk/company/"&$I94 -> https://find-and-update.company-information.service.gov.uk/company/00296805 | K94: taylor wimpey | M94: https://www.glassdoor.co.uk/Overview/Working-at-Taylor-Wimpey-EI_IE10247.11,24.htm
A95: ULVR | B95: Unilever | C95: {=xlookup(B95, sectors!A:A, sectors!A:A)} -> Unilever | D95: ULVR | E95: ULVR.L | F95: {=xlookup(A95, sectors!B:B, sectors!C:C)} -> Food & Beverage | G95: {=XLOOKUP(A95, sectors!B:B, sectors!E:E)} -> Personal Goods | H95: Unilever is a British multinational consumer packaged goods company headquartered in London, England. | I95: 00041424 | J95: ="https://find-and-update.company-information.service.gov.uk/company/"&$I95 -> https://find-and-update.company-information.service.gov.uk/company/00041424 | K95: unilever | L95: Unilever | M95: https://www.glassdoor.co.uk/Overview/Working-at-Unilever-EI_IE3513.11,19.htm
A96: UTG | B96: Unite Group | C96: {=xlookup(B96, sectors!A:A, sectors!A:A)} -> Unite Group | D96: =left(E96, 3) -> UTG | E96: UTG.L | F96: {=xlookup(A96, sectors!B:B, sectors!C:C)} -> Real Estate | G96: {=XLOOKUP(A96, sectors!B:B, sectors!E:E)} -> Real Estate | H96: The Unite Group provides purpose built student accommodation across the United Kingdom. The company is listed on the London Stock Exchange as a constituent of the FTSE 100 Index. | I96: 03199160 | J96: ="https://find-and-update.company-information.service.gov.uk/company/"&$I96 -> https://find-and-update.company-information.service.gov.uk/company/03199160 | K96: unite group, unite students | M96: https://www.glassdoor.co.uk/Overview/Working-at-Unite-Group-EI_IE907962.11,22.htm
A97: UU. | B97: United Utilities | C97: United Utilities Group | D97: =left(E97, 3) -> UU. | E97: UU.L | F97: {=xlookup(A97, sectors!B:B, sectors!C:C)} -> Utilities | G97: {=XLOOKUP(A97, sectors!B:B, sectors!E:E)} -> Gas, Water & Multi-utilities | H97: United Utilities Group plc (UU), the United Kingdom's largest listed water company, was founded in 1995 as a result of the merger of North West Water and NORWEB.[2] The group manages the regulated water and waste water network in North West England, which includes Cumbria, Greater Manchester, Lancashire, Merseyside, most of Cheshire and a small area of Derbyshire, which have a combined population of more than seven million. | I97: 06559020 | J97: ="https://find-and-update.company-information.service.gov.uk/company/"&$I97 -> https://find-and-update.company-information.service.gov.uk/company/06559020 | K97: united utilities | M97: https://www.glassdoor.co.uk/Overview/Working-at-United-Utilities-EI_IE7737.11,27.htm
A98: VOD | B98: Vodafone Group | C98: {=xlookup(B98, sectors!A:A, sectors!A:A)} -> Vodafone Group | D98: =left(E98, 3) -> VOD | E98: VOD.L | F98: {=xlookup(A98, sectors!B:B, sectors!C:C)} -> Retail & Services | G98: {=XLOOKUP(A98, sectors!B:B, sectors!E:E)} -> Mobile Telecommunications | H98: Vodafone Group Plc is a British multinational telecommunications company. Its registered office and global headquarters are in Newbury, Berkshire, England. It predominantly operates services in Asia, Africa, Europe, and Oceania. | I98: 01833679 | J98: ="https://find-and-update.company-information.service.gov.uk/company/"&$I98 -> https://find-and-update.company-information.service.gov.uk/company/01833679 | K98: vodafone | M98: https://www.glassdoor.co.uk/Overview/Working-at-Vodafone-EI_IE5775.11,19.htm
A99: WEIR | B99: Weir Group | C99: {=xlookup(B99, sectors!A:A, sectors!A:A)} -> Weir Group | D99: WEIR | E99: WEIR.L | F99: {=xlookup(A99, sectors!B:B, sectors!C:C)} -> Engineering & Construction | G99: {=XLOOKUP(A99, sectors!B:B, sectors!E:E)} -> Industrial Goods and Services | H99: The Weir Group plc is a Scottish multinational engineering company headquartered in Glasgow, Scotland. It is listed on the London Stock Exchange and is a constituent of the FTSE 100 Index. | I99: SC002934 | J99: ="https://find-and-update.company-information.service.gov.uk/company/"&$I99 -> https://find-and-update.company-information.service.gov.uk/company/SC002934 | K99: weir | M99: https://www.glassdoor.co.uk/Overview/Working-at-Weir-Group-EI_IE10268.11,21.htm
A100: WPP | B100: WPP | C100: WPP plc | D100: =left(E100, 3) -> WPP | E100: WPP.L | F100: {=xlookup(A100, sectors!B:B, sectors!C:C)} -> Retail & Services | G100: {=XLOOKUP(A100, sectors!B:B, sectors!E:E)} -> Media | H100: WPP plc is a British multinational communications, advertising, public relations, technology, and commerce holding company headquartered in London, England. It was the world's largest advertising company, as of 2019. | I100: 08286875 | J100: https://find-and-update.company-information.service.gov.uk/company/08286875/filing-history | K100: wpp | L100: WPP | M100: https://www.glassdoor.co.uk/Overview/Working-at-WPP-EI_IE4035.11,14.htm
...

Sheet sectors
A1: Company | B1: Ticker | C1: R100 sectors | D1: R100 industry | E1: R100 industries (based on FTSE wikipedias)
A2: BAE Systems | B2: BA. | C2: Engineering & Construction | D2: Aerospace & Defence | E2: Aerospace & Defence
A3: Rolls-Royce Holdings | B3: RR. | C3: Engineering & Construction | D3: Aerospace & Defence | E3: Aerospace & Defence
A4: M&G | B4: MNG | C4: Financial Services | D4: Asset Managers | E4: Asset Managers
A5: Melrose Industries | B5: MRO | C5: Engineering & Construction | D5: Automobiles & Parts | E5: Automobiles & Parts
A6: Barclays | B6: BARC | C6: Financial Services | D6: Banks | E6: Banks
A7: HSBC | B7: HSBA | C7: Financial Services | D7: Banking | E7: Banks
A8: Lloyds Banking Group | B8: LLOY | C8: Financial Services | D8: Banks | E8: Banks
A9: NatWest Group | B9: RBS | C9: Financial Services | D9: Banks | E9: Banks
A10: Standard Chartered | B10: STAN | C10: Financial Services | D10: Banks | E10: Banks
A11: Coca-Cola HBC | B11: CCH | C11: Food & Beverage | D11: Beverage | E11: Beverages
A12: Diageo | B12: DGE | C12: Food & Beverage | D12: Beverages | E12: Beverages
... A101: Centrica | B101: CNA | C101: Engineering & Construction | D101: Utilities | E101: Utilities

Sheet r100_pillar_descriptions
A1: Pillar | B1: Description | C1: Colour | D1: SDG
A2: Poverty and Wellbeing | B2: To what extent are companies protecting and supporting their employees as well as the consumers of their products? This is what the Poverty & Wellbeing pillar measures. | D2: Goal 1 - No poverty Goal 3 - Good health & wellbeing Goal 8 - Decent work and economic growth | E2: Goal 11 not assigned
A3: Skills and Education | B3: The Skills & Education pillar examines what level and quality of training companies are providing to their employees - and whether they're bringing their expertise to the wider community. | D3: Goal 4 - Quality education Goal 8 - Decent work and economic growth
A4: Equality | B4: Are companies treating all their staff equally? The Equality pillar examines the representation of protected groups. | D4: Goal 5 - Gender equality Goal 10 - Reduced inequalities
A5: Good Business | B5: From innovation to profit to tax, the Good Business pillar rewards companies for delivering on the core societal benefits of business. | D5: Goal 2 - Zero hunger Goal 8 - Decent work and economic growth Goal 9 - Industry, innovation and infrastructure Goal 12 - Responsible consumption and production
A6: Climate | B6: The Climate pillar focuses on the environmental impact of a company's operations, looking at emissions, water use and waste. | D6: Goal 6 - Clean water and sanitation Goal 7 - Affordable and clean energy Goal 13 - Climate action Goal 14 - Life below water Goal 15 - Life on land
A7: Justice | B7: A company's biggest offences in the eyes of regulators and the courts are reflected in the Justice pillar. | D7: Goal 5 - Gender equality Goal 10 - Reduced inequalities Goal 16 - Peace, justice and strong institutions
A8: Misc | B8: General information on a company. | D8: N/A
A9: Targets | B9: We collect data on targets as part of the talk pillar. The text of the targets we found can be found in the annex. | D9: Goal 17 - Partnerships for the goals
A10: Membership | B10: The Talk pillar measures how loudly companies are talking about responsibility, asking the question: What kind of commitments are companies making? Below are all of the membership metrics that feed into the talk score. | D10: Goal 16 - Peace, justice and strong institutions Goal 17 - Partnerships for the goals
A11: Modern Slavery | B11: Our Modern Slavery indicators feed into our Modern Slavery Score - a measure of a company's commitment to preventing, discovering and handling incidence of modern slavery, both operationally and along the supply chain.

Sheet target_categories
A1: ticker | B1: description | C1: Which target indicators?
A2: T106 | B2: Number of targets relating to Climate | C2: T021,T022, T023, T024, T030, T031, T032, T033, T045, T047, T048, T049, T050, T053, T100
A3: T107 | B3: Number of targets relating to equality | C3: T034, T035, T036, T037, T101
A4: T108 | B4: Number of targets relating to poverty and wellbeing | C4: T038, T040, T102
A5: T109 | B5: Number of targets relating to justice | C5: T044, T052, T054, T103
A6: T110 | B6: Number of targets relating to Skills | C6: T042, T055, T104
A7: T111 | B7: Number of targets relating to Good Business | C7: T039, T041, T043, T046, T051, T105

Sheet r100_codebook_mini
A1: Pillar | B1: Indicator Name | C1: Programmatic Name | D1: Code | E1: Description | F1: Unit | G1: Source
A2: Talk | B2: Count of words in reporting relating to Poverty and Wellbeing | C2: talk_wb_count | D2: T001 | E2: The total number of references to selected keywords in Annual Reporting, Sustainability Reports and Websites; in this case related to Poverty & Wellbeing. | F2: Count | G2: Annual Reports, Sustainability Reports and Company Websites
A3: Talk | B3: Count of words in reporting relating to Education and Skills | C3: talk_skills_count | D3: T002 | E3: The total number of references to selected keywords in Annual Reporting, Sustainability Reports and Websites; in this case related to Education & Skills | F3: Count | G3: Annual Reports, Sustainability Reports and Company Websites
A4: Talk | B4: Count of words in reporting relating to Equality | C4: talk_equality_count | D4: T003 | E4: The total number of references to selected keywords in Annual Reporting, Sustainability Reports and Websites; in this case related to Equality | F4: Count | G4: Annual Reports, Sustainability Reports and Company Websites
A5: Talk | B5: Count of words in reporting relating to Good Business | C5: talk_gb_count | D5: T004 | E5: The total number of references to selected keywords in Annual Reporting, Sustainability Reports and Websites; in this case related to Good Business | F5: Count | G5: Annual Reports, Sustainability Reports and Company Websites
A6: Talk | B6: Count of words in reporting relating to Climate | C6: talk_climate_count | D6: T005 | E6: The total number of references to selected keywords in Annual Reporting, Sustainability Reports and Websites; in this case related to Climate | F6: Count | G6: Annual Reports, Sustainability Reports and Company Websites
A7: Talk | B7: Count of words in reporting relating to Partnership | C7: talk_partnership_count | D7: T006 | E7: The total number of references to selected keywords in Annual Reporting, Sustainability Reports and Websites; in this case related to Partnership | F7: Count | G7: Annual Reports, Sustainability Reports and Company Websites
A8: Talk | B8: Count of words in reporting relating to Justice | C8: talk_justice_count | D8: T007 | E8: The total number of references to selected keywords in Annual Reporting, Sustainability Reports and Websites; in this case related to Justice | F8: Count | G8: Annual Reports, Sustainability Reports and Company Websites
A9: Talk | B9: Proportion of words in reporting relating to Poverty and Wellbeing | C9: talk_wb_pct | D9: T008 | E9: The total number of references to selected keywords in Annual Reporting, Sustainability Reports and Websites as a proportion of total word count in analysed text; in this case related to Poverty & Wellbeing | F9: Count | G9: Annual Reports, Sustainability Reports and Company Websites
A10: Talk | B10: Proportion of words in reporting relating to Education and Skills | C10: talk_skills_pct | D10: T009 | E10: The total number of references to selected keywords in Annual Reporting, Sustainability Reports and Websites as a proportion of total word count in analysed text; in this case related to Education & Skills | F10: Percentage | G10: Annual Reports, Sustainability Reports and Company Websites
A11: Talk | B11: Proportion of words in reporting relating to Equality | C11: talk_equality_pct | D11: T010 | E11: The total number of references to selected keywords in Annual Reporting, Sustainability Reports and Websites as a proportion of total word count in analysed text; in this case related to Equality | F11: Percentage | G11: Annual Reports, Sustainability Reports and Company Websites
A12: Talk | B12: Proportion of words in reporting relating to Good Business | C12: talk_gb_pct | D12: T011 | E12: The total number of references to selected keywords in Annual Reporting, Sustainability Reports and Websites as a proportion of total word count in analysed text; in this case related to Good Business | F12: Percentage | G12: Annual Reports, Sustainability Reports and Company Websites
... A127: Partnership | B127: Hours dedicated to charity | C127: partnership_hours | D127: P010 | E127: The number of hours a company's employees have spent volunteering for charitable and community organisations. | F127: Hours | G127: Annual Report, Sustainability Report
A128: Partnership | B128: Community, charity and social contributions reach | C128: partnership_contribs_reach | D128: P011
A129: Partnership | B129: Community, charity and social contributions (£) | C129: partnership_contribs | D129: P012 | E129: The total amount or value of charitable donations and volunteering by a company/group. | F129: GBP | G129: Annual Report, Sustainability Report
A130: Justice | B130: Number of fines relating to Planet | C130: justice_fines_planet_count | D130: J001 | E130: The total number of fines, settlements and other financial penalties related to environmental factors issued to the company/group by UK and US regulators since 2016. | F130: Count | G130: The regulatory bodies included are as follows, with the USA bodies having been compiled by Good Jobs First's Violations Tracker (https://www.goodjobsfirst.org/violation-tracker): ICO (UK), FMCSA (USA), USAO (USA), EPA (USA), OFCCP (USA), FRA (USA), OSHA (USA), CFTC (USA), DOJ (USA), ACPD (USA), MSHA (USA), EA (UK), BSEE (USA), OFGEM (UK), OFCOM (UK), Gambling Commission (UK), HSE (UK), OFAC (USA), FED (USA), SFO (UK), FCA (UK), FAA (USA)
A131: Justice | B131: Number of fines relating to People | C131: justice_fines_people_count | D131: J002 | E131: The total value of fines, settlements and other financial penalties related to social factors issued to the company/group by UK and US regulators since 2016. | F131: Count | G131: The regulatory bodies included are as follows, with the USA bodies having been compiled by Good Jobs First's Violations Tracker (https://www.goodjobsfirst.org/violation-tracker): ICO (UK), FMCSA (USA), USAO (USA), EPA (USA), OFCCP (USA), FRA (USA), OSHA (USA), CFTC (USA), DOJ (USA), ACPD (USA), MSHA (USA), EA (UK), BSEE (USA), OFGEM (UK), OFCOM (UK), Gambling Commission (UK), HSE (UK), OFAC (USA), FED (USA), SFO (UK), FCA (UK), FAA (USA)
A132: Justice | B132: Number of human rights accusations not responded to | C132: justice_accusations_response | D132: J003 | E132: The absolute number of human rights accusations, compiled by the Business and Human Rights Resource Centre, that have not been replied to by the company. | F132: Count | G132: BHRRC https://www.business-humanrights.org/
A133: Justice | B133: Response rate to human rights accusations | C133: justice_accusations_rate | D133: J004 | E133: The number of human rights accusations compiled by the Business and Human Rights Resource Centre that a company has responded to as a proportion of the total number of accusations compiled by the Centre. | F133: Percentage | G133: BHRRC https://www.business-humanrights.org/
A134: Justice | B134: BHRRC Modern Slavery Report ranking | C134: justice_slavery | D134: J005 | E134: A ranking by the Business and Human Rights Resource Centres of the FTSE100 companies on their compliance with the Modern Slavery Act. | F134: Rank | G134: BHRRC https://www.business-humanrights.org/
A135: Justice | B135: Value of People fines (£) | C135: justice_fines_people_value | D135: J006 | E135: The total value of fines, settlements and other financial penalties related to social factors issued to the company/group by UK and US regulators since 2016. | F135: GBP | G135: The regulatory bodies included are as follows, with the USA bodies having been compiled by Good Jobs First's Violations Tracker (https://www.goodjobsfirst.org/violation-tracker): ICO (UK), FMCSA (USA), USAO (USA), EPA (USA), OFCCP (USA), FRA (USA), OSHA (USA), CFTC (USA), DOJ (USA), ACPD (USA), MSHA (USA), EA (UK), BSEE (USA), OFGEM (UK), OFCOM (UK), Gambling Commission (UK), HSE (UK), OFAC (USA), FED (USA), SFO (UK), FCA (UK), FAA (USA)
A136: Justice | B136: Value of People fines as a proportion of revenue (%) | C136: justice_fines_people_value_revenue | D136: J007 | E136: The total value of fines, settlements and other financial penalties related to social factors issued to the company/group by UK and US regulators since 2016 as a proportion of total revenue reported by the company/group in the most recently reported year. | F136: Percentage | G136: The regulatory bodies included are as follows, with the USA bodies having been compiled by Good Jobs First's Violations Tracker (https://www.goodjobsfirst.org/violation-tracker): ICO (UK), FMCSA (USA), USAO (USA), EPA (USA), OFCCP (USA), FRA (USA), OSHA (USA), CFTC (USA), DOJ (USA), ACPD (USA), MSHA (USA), EA (UK), BSEE (USA), OFGEM (UK), OFCOM (UK), Gambling Commission (UK), HSE (UK), OFAC (USA), FED (USA), SFO (UK), FCA (UK), FAA (USA)
A137: Justice | B137: Value of Planet fines (£) | C137: justice_fines_planet_value | D137: J008 | E137: The total value of fines, settlements and other financial penalties related to environmental factors issued to the company/group by UK and US regulators since 2016. | F137: GBP | G137: The regulatory bodies included are as follows, with the USA bodies having been compiled by Good Jobs First's Violations Tracker (https://www.goodjobsfirst.org/violation-tracker): ICO (UK), FMCSA (USA), USAO (USA), EPA (USA), OFCCP (USA), FRA (USA), OSHA (USA), CFTC (USA), DOJ (USA), ACPD (USA), MSHA (USA), EA (UK), BSEE (USA), OFGEM (UK), OFCOM (UK), Gambling Commission (UK), HSE (UK), OFAC (USA), FED (USA), SFO (UK), FCA (UK), FAA (USA)
A138: Justice | B138: Value of Planet fines as a proportion of revenue (%) | C138: justice_fines_planet_value_revenue | D138: J009 | E138: The total value of fines, settlements and other financial penalties related to environmental factors issued to the company/group by UK and US regulators since 2016 as a proportion of total revenue reported by the company/group in the most recently reported year. | F138: Percentage | G138: The regulatory bodies included are as follows, with the USA bodies having been compiled by Good Jobs First's Violations Tracker (https://www.goodjobsfirst.org/violation-tracker): ICO (UK), FMCSA (USA), USAO (USA), EPA (USA), OFCCP (USA), FRA (USA), OSHA (USA), CFTC (USA), DOJ (USA), ACPD (USA), MSHA (USA), EA (UK), BSEE (USA), OFGEM (UK), OFCOM (UK), Gambling Commission (UK), HSE (UK), OFAC (USA), FED (USA), SFO (UK), FCA (UK), FAA (USA)
A139: Justice | B139: Number of upheld employment tribunal cases | C139: justice_et_upheld | D139: J010 | E139: The total number of UK Employment Tribunal cases since 2017 involving the company which saw the Tribunal uphold at least one of the claims of the employee/former employee. | F139: Count | G139: UK Employment Tribunal
A140: Justice | B140: Number of upheld employment tribunal cases per employee | C140: justice_et_upheld_employees | D140: J011 | E140: The total number of UK Employment Tribunal cases since 2017 involving the company which saw the Tribunal uphold at least one of the claims of the employee/former employee as a proportion of total number of employees. | F140: Percentage | G140: UK Employment Tribunal
... A144: Misc | B144: Number of employees in previous year | C144: misc_employees_previous | D144: M002 | E144: The total number of people employed by a company/group in the previously reported year. If reported, we have used FTE or average number of employees. | F144: Count | G144: Annual Report
A145: Misc | B145: Market capitalisation | C145: misc_cap | D145: M003 | G145: London Stock Exchange
